{
    "modified": 1424358216,
    "modified_str": "2015-02-19 15:03:36",
    "stability": {
        "2014-06-29": {
            "period": {
                "4": 0.41635321,
                "13": 0.90295312,
                "26": 0.67852181,
                "52": 0.80705399
            },
            "price": 11275
        },
        "2014-07-06": {
            "period": {
                "4": 0.47982774,
                "13": 0.78711855,
                "26": 0.7577713,
                "52": 0.76612951
            },
            "price": 11347
        },
        "2014-07-13": {
            "period": {
                "4": 0.35851761,
                "13": 0.72044955,
                "26": 0.80056688,
                "52": 0.77341418
            },
            "price": 11277
        },
        "2014-07-20": {
            "period": {
                "4": 0.64516575,
                "13": 0.79570923,
                "26": 0.8194042,
                "52": 0.72780833
            },
            "price": 11288
        },
        "2014-07-27": {
            "period": {
                "4": 0.75757497,
                "13": 0.82899176,
                "26": 0.89389575,
                "52": 0.69946436
            },
            "price": 11483
        },
        "2014-08-03": {
            "period": {
                "4": 0.66682177,
                "13": 0.77429021,
                "26": 0.9628734,
                "52": 0.76675768
            },
            "price": 11278
        },
        "2014-08-10": {
            "period": {
                "4": 0.33467663,
                "13": 0.48764694,
                "26": 0.92137694,
                "52": 0.74670304
            },
            "price": 11109
        },
        "2014-08-17": {
            "period": {
                "4": 0.34071741,
                "13": 0.40215206,
                "26": 0.86489442,
                "52": 0.75062006
            },
            "price": 11262
        },
        "2014-08-24": {
            "period": {
                "4": 0.37097498,
                "13": 0.54816447,
                "26": 0.86336071,
                "52": 0.80349646
            },
            "price": 11370
        },
        "2014-08-31": {
            "period": {
                "4": 0.52456821,
                "13": 0.58275952,
                "26": 0.89303975,
                "52": 0.87667914
            },
            "price": 11438
        },
        "2014-09-07": {
            "period": {
                "4": 0.92106804,
                "13": 0.66226732,
                "26": 0.9057864,
                "52": 0.89490948
            },
            "price": 11545
        },
        "2014-09-14": {
            "period": {
                "4": 0.98520473,
                "13": 0.58704903,
                "26": 0.9133119,
                "52": 0.86808633
            },
            "price": 11472
        },
        "2014-09-21": {
            "period": {
                "4": 0.88211455,
                "13": 0.70568478,
                "26": 0.93843827,
                "52": 0.82819731
            },
            "price": 11528
        },
        "2014-09-28": {
            "period": {
                "4": 0.59161873,
                "13": 0.66116938,
                "26": 0.90128605,
                "52": 0.81899962
            },
            "price": 11294
        },
        "2014-10-05": {
            "period": {
                "4": 0.1370539,
                "13": 0.45686466,
                "26": 0.68805399,
                "52": 0.83431021
            },
            "price": 11206
        },
        "2014-10-12": {
            "period": {
                "4": 0.09693064,
                "13": 0.40883779,
                "26": 0.58473359,
                "52": 0.80252758
            },
            "price": 11186
        },
        "2014-10-19": {
            "period": {
                "4": 0.0346519,
                "13": 0.28863903,
                "26": 0.52855255,
                "52": 0.70079828
            },
            "price": 10915
        },
        "2014-10-26": {
            "period": {
                "4": 0.27809702,
                "13": 0.38240935,
                "26": 0.61835198,
                "52": 0.72738139
            },
            "price": 11384
        },
        "2014-11-02": {
            "period": {
                "4": 0.6972339,
                "13": 0.56452035,
                "26": 0.71163039,
                "52": 0.79528591
            },
            "price": 11640
        },
        "2014-11-09": {
            "period": {
                "4": 0.88357227,
                "13": 0.82240846,
                "26": 0.77129004,
                "52": 0.86668957
            },
            "price": 11935
        },
        "2014-11-16": {
            "period": {
                "4": 0.99139193,
                "13": 0.87805622,
                "26": 0.79142287,
                "52": 0.89455772
            },
            "price": 12121
        },
        "2014-11-23": {
            "period": {
                "4": 0.9999756,
                "13": 0.90569235,
                "26": 0.87520263,
                "52": 0.89256244
            },
            "price": 12364
        },
        "2014-11-30": {
            "period": {
                "4": 0.99996258,
                "13": 0.90711794,
                "26": 0.88587112,
                "52": 0.88386939
            },
            "price": 12423
        },
        "2014-12-07": {
            "period": {
                "4": 0.98854644,
                "13": 0.88343469,
                "26": 0.88775462,
                "52": 0.88250284
            },
            "price": 12402
        },
        "2014-12-14": {
            "period": {
                "4": 0.6863156,
                "13": 0.79834681,
                "26": 0.79495056,
                "52": 0.83425565
            },
            "price": 11999
        },
        "2014-12-21": {
            "period": {
                "4": 0.14950964,
                "13": 0.55891532,
                "26": 0.63038439,
                "52": 0.69757288
            },
            "price": 11698
        },
        "2014-12-28": {
            "period": {
                "4": 0.23473943,
                "13": 0.65896027,
                "26": 0.70004141,
                "52": 0.75566872
            },
            "price": 11924
        },
        "2015-01-04": {
            "period": {
                "4": 0.29342104,
                "13": 0.75964718,
                "26": 0.71980294,
                "52": 0.81309194
            },
            "price": 11963
        },
        "2015-01-11": {
            "period": {
                "4": 0.35280222,
                "13": 0.74273694,
                "26": 0.68632951,
                "52": 0.81846377
            },
            "price": 11965
        },
        "2015-01-18": {
            "period": {
                "4": 0.72444912,
                "13": 0.80404366,
                "26": 0.69226869,
                "52": 0.83254377
            },
            "price": 11741
        },
        "2015-01-25": {
            "period": {
                "4": 0.31099184,
                "13": 0.69213981,
                "26": 0.60856436,
                "52": 0.83872378
            },
            "price": 11741
        },
        "2015-02-01": {
            "period": {
                "4": 0.12161274,
                "13": 0.54094521,
                "26": 0.56967506,
                "52": 0.87719226
            },
            "price": 11458
        },
        "2015-02-08": {
            "period": {
                "4": 0.0700343,
                "13": 0.30612249,
                "26": 0.56025483,
                "52": 0.82926384
            },
            "price": 11362
        }
    }
}