{
    "modified": 1424273709,
    "modified_str": "2015-02-18 15:35:09",
    "stability": {
        "2013-02-03": {
            "ratio": {
                "1.0": 0.9574,
                "1.1": 0.6888,
                "1.2": 0.2583,
                "1.3": 0.043
            },
            "threshold": {
                "0.50": 1.1424,
                "0.75": 1.2024,
                "0.90": 1.2586,
                "0.99": 1.3602
            },
            "price": 11514
        },
        "2013-02-10": {
            "ratio": {
                "1.0": 0.9548,
                "1.1": 0.6759,
                "1.2": 0.2439,
                "1.3": 0.0383
            },
            "threshold": {
                "0.50": 1.1388,
                "0.75": 1.1983,
                "0.90": 1.2538,
                "0.99": 1.3542
            },
            "price": 11615
        },
        "2013-02-17": {
            "ratio": {
                "1.0": 0.9464,
                "1.1": 0.6425,
                "1.2": 0.2145,
                "1.3": 0.0306
            },
            "threshold": {
                "0.50": 1.1309,
                "0.75": 1.1897,
                "0.90": 1.2447,
                "0.99": 1.3441
            },
            "price": 11600
        },
        "2013-02-24": {
            "ratio": {
                "1.0": 0.9195,
                "1.1": 0.5517,
                "1.2": 0.1469,
                "1.3": 0.0157
            },
            "threshold": {
                "0.50": 1.1107,
                "0.75": 1.1674,
                "0.90": 1.2205,
                "0.99": 1.3167
            },
            "price": 11540
        },
        "2013-03-03": {
            "ratio": {
                "1.0": 0.8779,
                "1.1": 0.4542,
                "1.2": 0.097,
                "1.3": 0.0082
            },
            "threshold": {
                "0.50": 1.0907,
                "0.75": 1.1464,
                "0.90": 1.1985,
                "0.99": 1.2932
            },
            "price": 11543
        },
        "2013-03-10": {
            "ratio": {
                "1.0": 0.9018,
                "1.1": 0.5059,
                "1.2": 0.1213,
                "1.3": 0.0116
            },
            "threshold": {
                "0.50": 1.1012,
                "0.75": 1.1574,
                "0.90": 1.21,
                "0.99": 1.3053
            },
            "price": 11724
        },
        "2013-03-17": {
            "ratio": {
                "1.0": 0.9092,
                "1.1": 0.5225,
                "1.2": 0.1286,
                "1.3": 0.0123
            },
            "threshold": {
                "0.50": 1.1046,
                "0.75": 1.1607,
                "0.90": 1.213,
                "0.99": 1.3073
            },
            "price": 11821
        },
        "2013-03-24": {
            "ratio": {
                "1.0": 0.9039,
                "1.1": 0.5064,
                "1.2": 0.1189,
                "1.3": 0.0107
            },
            "threshold": {
                "0.50": 1.1013,
                "0.75": 1.1568,
                "0.90": 1.2088,
                "0.99": 1.3025
            },
            "price": 11716
        },
        "2013-03-31": {
            "ratio": {
                "1.0": 0.9147,
                "1.1": 0.53,
                "1.2": 0.1296,
                "1.3": 0.0121
            },
            "threshold": {
                "0.50": 1.1061,
                "0.75": 1.1615,
                "0.90": 1.2132,
                "0.99": 1.3067
            },
            "price": 11725
        },
        "2013-04-07": {
            "ratio": {
                "1.0": 0.9197,
                "1.1": 0.5447,
                "1.2": 0.1383,
                "1.3": 0.0135
            },
            "threshold": {
                "0.50": 1.1092,
                "0.75": 1.1649,
                "0.90": 1.2168,
                "0.99": 1.3106
            },
            "price": 11847
        },
        "2013-04-14": {
            "ratio": {
                "1.0": 0.9698,
                "1.1": 0.7352,
                "1.2": 0.3033,
                "1.3": 0.0588
            },
            "threshold": {
                "0.50": 1.154,
                "0.75": 1.2147,
                "0.90": 1.2723,
                "0.99": 1.3782
            },
            "price": 12134
        },
        "2013-04-21": {
            "ratio": {
                "1.0": 0.9516,
                "1.1": 0.6776,
                "1.2": 0.2608,
                "1.3": 0.0488
            },
            "threshold": {
                "0.50": 1.1409,
                "0.75": 1.2032,
                "0.90": 1.2623,
                "0.99": 1.3708
            },
            "price": 11857
        },
        "2013-04-28": {
            "ratio": {
                "1.0": 0.9579,
                "1.1": 0.7105,
                "1.2": 0.3005,
                "1.3": 0.0644
            },
            "threshold": {
                "0.50": 1.1505,
                "0.75": 1.2147,
                "0.90": 1.2756,
                "0.99": 1.3872
            },
            "price": 12084
        },
        "2013-05-05": {
            "ratio": {
                "1.0": 0.9602,
                "1.1": 0.7213,
                "1.2": 0.3136,
                "1.3": 0.0698
            },
            "threshold": {
                "0.50": 1.1537,
                "0.75": 1.2185,
                "0.90": 1.2797,
                "0.99": 1.3922
            },
            "price": 11996
        },
        "2013-05-12": {
            "ratio": {
                "1.0": 0.9812,
                "1.1": 0.8175,
                "1.2": 0.4313,
                "1.3": 0.1208
            },
            "threshold": {
                "0.50": 1.1834,
                "0.75": 1.2493,
                "0.90": 1.3117,
                "0.99": 1.4263
            },
            "price": 12305
        },
        "2013-05-19": {
            "ratio": {
                "1.0": 0.9943,
                "1.1": 0.9061,
                "1.2": 0.5811,
                "1.3": 0.206
            },
            "threshold": {
                "0.50": 1.2193,
                "0.75": 1.2853,
                "0.90": 1.3478,
                "0.99": 1.463
            },
            "price": 12291
        },
        "2013-05-26": {
            "ratio": {
                "1.0": 0.9976,
                "1.1": 0.9389,
                "1.2": 0.6515,
                "1.3": 0.2513
            },
            "threshold": {
                "0.50": 1.2358,
                "0.75": 1.3006,
                "0.90": 1.3619,
                "0.99": 1.4754
            },
            "price": 12204
        },
        "2013-06-02": {
            "ratio": {
                "1.0": 0.9946,
                "1.1": 0.9087,
                "1.2": 0.5866,
                "1.3": 0.2099
            },
            "threshold": {
                "0.50": 1.2207,
                "0.75": 1.2867,
                "0.90": 1.3493,
                "0.99": 1.4645
            },
            "price": 12017
        },
        "2013-06-09": {
            "ratio": {
                "1.0": 0.988,
                "1.1": 0.8612,
                "1.2": 0.5042,
                "1.3": 0.1625
            },
            "threshold": {
                "0.50": 1.2011,
                "0.75": 1.2681,
                "0.90": 1.3316,
                "0.99": 1.4483
            },
            "price": 11692
        },
        "2013-06-16": {
            "ratio": {
                "1.0": 0.9644,
                "1.1": 0.7519,
                "1.2": 0.3614,
                "1.3": 0.0943
            },
            "threshold": {
                "0.50": 1.1649,
                "0.75": 1.2326,
                "0.90": 1.2965,
                "0.99": 1.4141
            },
            "price": 11473
        },
        "2013-06-23": {
            "ratio": {
                "1.0": 0.9407,
                "1.1": 0.6745,
                "1.2": 0.2853,
                "1.3": 0.0653
            },
            "threshold": {
                "0.50": 1.1434,
                "0.75": 1.2111,
                "0.90": 1.2751,
                "0.99": 1.3928
            },
            "price": 11320
        },
        "2013-06-30": {
            "ratio": {
                "1.0": 0.9369,
                "1.1": 0.6677,
                "1.2": 0.2828,
                "1.3": 0.0657
            },
            "threshold": {
                "0.50": 1.142,
                "0.75": 1.2103,
                "0.90": 1.2751,
                "0.99": 1.394
            },
            "price": 11500
        },
        "2013-07-07": {
            "ratio": {
                "1.0": 0.9351,
                "1.1": 0.6592,
                "1.2": 0.2713,
                "1.3": 0.06
            },
            "threshold": {
                "0.50": 1.1394,
                "0.75": 1.2067,
                "0.90": 1.2705,
                "0.99": 1.3874
            },
            "price": 11603
        },
        "2013-07-14": {
            "ratio": {
                "1.0": 0.9506,
                "1.1": 0.7038,
                "1.2": 0.3098,
                "1.3": 0.0726
            },
            "threshold": {
                "0.50": 1.151,
                "0.75": 1.2181,
                "0.90": 1.2813,
                "0.99": 1.3971
            },
            "price": 11716
        },
        "2013-07-21": {
            "ratio": {
                "1.0": 0.9602,
                "1.1": 0.7396,
                "1.2": 0.3492,
                "1.3": 0.0889
            },
            "threshold": {
                "0.50": 1.1616,
                "0.75": 1.2292,
                "0.90": 1.293,
                "0.99": 1.4096
            },
            "price": 11848
        },
        "2013-07-28": {
            "ratio": {
                "1.0": 0.9727,
                "1.1": 0.7879,
                "1.2": 0.4043,
                "1.3": 0.1123
            },
            "threshold": {
                "0.50": 1.1761,
                "0.75": 1.2437,
                "0.90": 1.3072,
                "0.99": 1.4233
            },
            "price": 11786
        },
        "2013-08-04": {
            "ratio": {
                "1.0": 0.9572,
                "1.1": 0.7262,
                "1.2": 0.3323,
                "1.3": 0.0811
            },
            "threshold": {
                "0.50": 1.1573,
                "0.75": 1.2245,
                "0.90": 1.2876,
                "0.99": 1.4034
            },
            "price": 11751
        },
        "2013-08-11": {
            "ratio": {
                "1.0": 0.9363,
                "1.1": 0.6557,
                "1.2": 0.262,
                "1.3": 0.0546
            },
            "threshold": {
                "0.50": 1.1377,
                "0.75": 1.2037,
                "0.90": 1.266,
                "0.99": 1.3802
            },
            "price": 11596
        },
        "2013-08-18": {
            "ratio": {
                "1.0": 0.9281,
                "1.1": 0.6336,
                "1.2": 0.2442,
                "1.3": 0.0491
            },
            "threshold": {
                "0.50": 1.1322,
                "0.75": 1.1982,
                "0.90": 1.2605,
                "0.99": 1.3747
            },
            "price": 11602
        },
        "2013-08-25": {
            "ratio": {
                "1.0": 0.9089,
                "1.1": 0.5872,
                "1.2": 0.21,
                "1.3": 0.0393
            },
            "threshold": {
                "0.50": 1.1209,
                "0.75": 1.1867,
                "0.90": 1.2491,
                "0.99": 1.3633
            },
            "price": 11569
        },
        "2013-09-01": {
            "ratio": {
                "1.0": 0.917,
                "1.1": 0.6064,
                "1.2": 0.2239,
                "1.3": 0.0432
            },
            "threshold": {
                "0.50": 1.1255,
                "0.75": 1.1915,
                "0.90": 1.2538,
                "0.99": 1.3681
            },
            "price": 11499
        },
        "2013-09-08": {
            "ratio": {
                "1.0": 0.9259,
                "1.1": 0.6311,
                "1.2": 0.2445,
                "1.3": 0.0498
            },
            "threshold": {
                "0.50": 1.1318,
                "0.75": 1.1983,
                "0.90": 1.261,
                "0.99": 1.3759
            },
            "price": 11632
        },
        "2013-09-15": {
            "ratio": {
                "1.0": 0.9339,
                "1.1": 0.6572,
                "1.2": 0.2704,
                "1.3": 0.0597
            },
            "threshold": {
                "0.50": 1.1389,
                "0.75": 1.2065,
                "0.90": 1.2702,
                "0.99": 1.3871
            },
            "price": 11789
        },
        "2013-09-22": {
            "ratio": {
                "1.0": 0.9394,
                "1.1": 0.6759,
                "1.2": 0.2901,
                "1.3": 0.0679
            },
            "threshold": {
                "0.50": 1.1443,
                "0.75": 1.2126,
                "0.90": 1.2771,
                "0.99": 1.3953
            },
            "price": 12031
        },
        "2013-09-29": {
            "ratio": {
                "1.0": 0.9486,
                "1.1": 0.7076,
                "1.2": 0.3242,
                "1.3": 0.0824
            },
            "threshold": {
                "0.50": 1.1536,
                "0.75": 1.2229,
                "0.90": 1.2883,
                "0.99": 1.4079
            },
            "price": 11885
        },
        "2013-10-06": {
            "ratio": {
                "1.0": 0.929,
                "1.1": 0.6518,
                "1.2": 0.273,
                "1.3": 0.0633
            },
            "threshold": {
                "0.50": 1.1384,
                "0.75": 1.2074,
                "0.90": 1.2728,
                "0.99": 1.3926
            },
            "price": 11771
        },
        "2013-10-13": {
            "ratio": {
                "1.0": 0.9281,
                "1.1": 0.6498,
                "1.2": 0.2714,
                "1.3": 0.0628
            },
            "threshold": {
                "0.50": 1.1378,
                "0.75": 1.207,
                "0.90": 1.2723,
                "0.99": 1.3922
            },
            "price": 11882
        },
        "2013-10-20": {
            "ratio": {
                "1.0": 0.9366,
                "1.1": 0.6745,
                "1.2": 0.2951,
                "1.3": 0.0721
            },
            "threshold": {
                "0.50": 1.1448,
                "0.75": 1.2143,
                "0.90": 1.2802,
                "0.99": 1.4007
            },
            "price": 12007
        },
        "2013-10-27": {
            "ratio": {
                "1.0": 0.9415,
                "1.1": 0.6895,
                "1.2": 0.3098,
                "1.3": 0.078
            },
            "threshold": {
                "0.50": 1.149,
                "0.75": 1.2188,
                "0.90": 1.2848,
                "0.99": 1.4057
            },
            "price": 11969
        },
        "2013-11-03": {
            "ratio": {
                "1.0": 0.9443,
                "1.1": 0.6978,
                "1.2": 0.3178,
                "1.3": 0.0811
            },
            "threshold": {
                "0.50": 1.1513,
                "0.75": 1.2212,
                "0.90": 1.2872,
                "0.99": 1.408
            },
            "price": 11981
        },
        "2013-11-10": {
            "ratio": {
                "1.0": 0.9358,
                "1.1": 0.6727,
                "1.2": 0.2937,
                "1.3": 0.0717
            },
            "threshold": {
                "0.50": 1.1443,
                "0.75": 1.214,
                "0.90": 1.2798,
                "0.99": 1.4005
            },
            "price": 11853
        },
        "2013-11-17": {
            "ratio": {
                "1.0": 0.9418,
                "1.1": 0.6904,
                "1.2": 0.3109,
                "1.3": 0.0785
            },
            "threshold": {
                "0.50": 1.1492,
                "0.75": 1.2192,
                "0.90": 1.2852,
                "0.99": 1.4062
            },
            "price": 11996
        },
        "2013-11-24": {
            "ratio": {
                "1.0": 0.9371,
                "1.1": 0.6743,
                "1.2": 0.2932,
                "1.3": 0.0707
            },
            "threshold": {
                "0.50": 1.1444,
                "0.75": 1.2137,
                "0.90": 1.2792,
                "0.99": 1.3989
            },
            "price": 12016
        },
        "2013-12-01": {
            "ratio": {
                "1.0": 0.9301,
                "1.1": 0.6527,
                "1.2": 0.2717,
                "1.3": 0.062
            },
            "threshold": {
                "0.50": 1.1384,
                "0.75": 1.207,
                "0.90": 1.2719,
                "0.99": 1.3907
            },
            "price": 12116
        },
        "2013-12-08": {
            "ratio": {
                "1.0": 0.9218,
                "1.1": 0.6308,
                "1.2": 0.2532,
                "1.3": 0.0557
            },
            "threshold": {
                "0.50": 1.1326,
                "0.75": 1.2011,
                "0.90": 1.2658,
                "0.99": 1.3846
            },
            "price": 12020
        },
        "2013-12-15": {
            "ratio": {
                "1.0": 0.9125,
                "1.1": 0.6068,
                "1.2": 0.2332,
                "1.3": 0.0489
            },
            "threshold": {
                "0.50": 1.1264,
                "0.75": 1.1945,
                "0.90": 1.2589,
                "0.99": 1.3771
            },
            "price": 12075
        },
        "2013-12-22": {
            "ratio": {
                "1.0": 0.8939,
                "1.1": 0.5628,
                "1.2": 0.1995,
                "1.3": 0.0383
            },
            "threshold": {
                "0.50": 1.1153,
                "0.75": 1.1826,
                "0.90": 1.2463,
                "0.99": 1.3637
            },
            "price": 12130
        },
        "2013-12-29": {
            "ratio": {
                "1.0": 0.8906,
                "1.1": 0.555,
                "1.2": 0.1937,
                "1.3": 0.0365
            },
            "threshold": {
                "0.50": 1.1134,
                "0.75": 1.1805,
                "0.90": 1.2441,
                "0.99": 1.3611
            },
            "price": 12221
        },
        "2014-01-05": {
            "ratio": {
                "1.0": 0.8811,
                "1.1": 0.5333,
                "1.2": 0.1778,
                "1.3": 0.0317
            },
            "threshold": {
                "0.50": 1.108,
                "0.75": 1.1746,
                "0.90": 1.2375,
                "0.99": 1.3535
            },
            "price": 12262
        },
        "2014-01-12": {
            "ratio": {
                "1.0": 0.8313,
                "1.1": 0.4424,
                "1.2": 0.1238,
                "1.3": 0.0184
            },
            "threshold": {
                "0.50": 1.0864,
                "0.75": 1.1513,
                "0.90": 1.213,
                "0.99": 1.327
            },
            "price": 12165
        },
        "2014-01-19": {
            "ratio": {
                "1.0": 0.8019,
                "1.1": 0.3966,
                "1.2": 0.1008,
                "1.3": 0.0135
            },
            "threshold": {
                "0.50": 1.0756,
                "0.75": 1.1396,
                "0.90": 1.2005,
                "0.99": 1.3131
            },
            "price": 12204
        },
        "2014-01-26": {
            "ratio": {
                "1.0": 0.7848,
                "1.1": 0.3737,
                "1.2": 0.0908,
                "1.3": 0.0117
            },
            "threshold": {
                "0.50": 1.07,
                "0.75": 1.1338,
                "0.90": 1.1945,
                "0.99": 1.3067
            },
            "price": 12134
        },
        "2014-02-02": {
            "ratio": {
                "1.0": 0.7024,
                "1.1": 0.2861,
                "1.2": 0.059,
                "1.3": 0.0066
            },
            "threshold": {
                "0.50": 1.0473,
                "0.75": 1.1106,
                "0.90": 1.1709,
                "0.99": 1.2827
            },
            "price": 11994
        },
        "2014-02-09": {
            "ratio": {
                "1.0": 0.6277,
                "1.1": 0.2201,
                "1.2": 0.0385,
                "1.3": 0.0037
            },
            "threshold": {
                "0.50": 1.0287,
                "0.75": 1.0908,
                "0.90": 1.15,
                "0.99": 1.2602
            },
            "price": 11974
        },
        "2014-02-16": {
            "ratio": {
                "1.0": 0.6588,
                "1.1": 0.2479,
                "1.2": 0.0472,
                "1.3": 0.0049
            },
            "threshold": {
                "0.50": 1.0364,
                "0.75": 1.0994,
                "0.90": 1.1595,
                "0.99": 1.2712
            },
            "price": 12080
        },
        "2014-02-23": {
            "ratio": {
                "1.0": 0.6914,
                "1.1": 0.2776,
                "1.2": 0.0568,
                "1.3": 0.0063
            },
            "threshold": {
                "0.50": 1.0447,
                "0.75": 1.1083,
                "0.90": 1.1688,
                "0.99": 1.2812
            },
            "price": 12152
        },
        "2014-03-02": {
            "ratio": {
                "1.0": 0.7298,
                "1.1": 0.3147,
                "1.2": 0.0693,
                "1.3": 0.0082
            },
            "threshold": {
                "0.50": 1.0547,
                "0.75": 1.1186,
                "0.90": 1.1793,
                "0.99": 1.2919
            },
            "price": 12169
        },
        "2014-03-09": {
            "ratio": {
                "1.0": 0.7084,
                "1.1": 0.2908,
                "1.2": 0.0602,
                "1.3": 0.0067
            },
            "threshold": {
                "0.50": 1.0488,
                "0.75": 1.1119,
                "0.90": 1.1721,
                "0.99": 1.2836
            },
            "price": 12292
        },
        "2014-03-16": {
            "ratio": {
                "1.0": 0.6454,
                "1.1": 0.2321,
                "1.2": 0.0412,
                "1.3": 0.0039
            },
            "threshold": {
                "0.50": 1.0327,
                "0.75": 1.0946,
                "0.90": 1.1536,
                "0.99": 1.263
            },
            "price": 12087
        },
        "2014-03-23": {
            "ratio": {
                "1.0": 0.6326,
                "1.1": 0.2228,
                "1.2": 0.0388,
                "1.3": 0.0036
            },
            "threshold": {
                "0.50": 1.0297,
                "0.75": 1.0917,
                "0.90": 1.1506,
                "0.99": 1.2601
            },
            "price": 12100
        },
        "2014-03-30": {
            "ratio": {
                "1.0": 0.6608,
                "1.1": 0.2456,
                "1.2": 0.0452,
                "1.3": 0.0045
            },
            "threshold": {
                "0.50": 1.0366,
                "0.75": 1.0988,
                "0.90": 1.158,
                "0.99": 1.2678
            },
            "price": 12181
        },
        "2014-04-06": {
            "ratio": {
                "1.0": 0.7132,
                "1.1": 0.2969,
                "1.2": 0.0625,
                "1.3": 0.0071
            },
            "threshold": {
                "0.50": 1.0502,
                "0.75": 1.1136,
                "0.90": 1.174,
                "0.99": 1.2857
            },
            "price": 12349
        },
        "2014-04-13": {
            "ratio": {
                "1.0": 0.5983,
                "1.1": 0.1809,
                "1.2": 0.0235,
                "1.3": 0.0014
            },
            "threshold": {
                "0.50": 1.0208,
                "0.75": 1.079,
                "0.90": 1.1336,
                "0.99": 1.2332
            },
            "price": 12246
        },
        "2014-04-20": {
            "ratio": {
                "1.0": 0.6486,
                "1.1": 0.2076,
                "1.2": 0.0274,
                "1.3": 0.0016
            },
            "threshold": {
                "0.50": 1.0311,
                "0.75": 1.0878,
                "0.90": 1.1413,
                "0.99": 1.2385
            },
            "price": 12321
        },
        "2014-04-27": {
            "ratio": {
                "1.0": 0.6215,
                "1.1": 0.1796,
                "1.2": 0.0201,
                "1.3": 0.0009
            },
            "threshold": {
                "0.50": 1.0245,
                "0.75": 1.0796,
                "0.90": 1.1313,
                "0.99": 1.2253
            },
            "price": 12298
        },
        "2014-05-04": {
            "ratio": {
                "1.0": 0.6085,
                "1.1": 0.1689,
                "1.2": 0.0178,
                "1.3": 0.0008
            },
            "threshold": {
                "0.50": 1.0216,
                "0.75": 1.0763,
                "0.90": 1.1276,
                "0.99": 1.2207
            },
            "price": 12313
        },
        "2014-05-11": {
            "ratio": {
                "1.0": 0.5644,
                "1.1": 0.1346,
                "1.2": 0.0113,
                "1.3": 0.0004
            },
            "threshold": {
                "0.50": 1.0124,
                "0.75": 1.0652,
                "0.90": 1.1146,
                "0.99": 1.2039
            },
            "price": 12325
        },
        "2014-05-18": {
            "ratio": {
                "1.0": 0.5273,
                "1.1": 0.1098,
                "1.2": 0.0074,
                "1.3": 0.0002
            },
            "threshold": {
                "0.50": 1.0051,
                "0.75": 1.0565,
                "0.90": 1.1044,
                "0.99": 1.1905
            },
            "price": 12353
        },
        "2014-05-25": {
            "ratio": {
                "1.0": 0.5407,
                "1.1": 0.1161,
                "1.2": 0.008,
                "1.3": 0.0002
            },
            "threshold": {
                "0.50": 1.0076,
                "0.75": 1.0591,
                "0.90": 1.1069,
                "0.99": 1.1932
            },
            "price": 12398
        },
        "2014-06-01": {
            "ratio": {
                "1.0": 0.649,
                "1.1": 0.1714,
                "1.2": 0.0141,
                "1.3": 0.0004
            },
            "threshold": {
                "0.50": 1.0281,
                "0.75": 1.0789,
                "0.90": 1.1261,
                "0.99": 1.2109
            },
            "price": 12406
        },
        "2014-06-08": {
            "ratio": {
                "1.0": 0.7688,
                "1.1": 0.2554,
                "1.2": 0.0252,
                "1.3": 0.0007
            },
            "threshold": {
                "0.50": 1.0519,
                "0.75": 1.1013,
                "0.90": 1.1473,
                "0.99": 1.2297
            },
            "price": 12465
        },
        "2014-06-15": {
            "ratio": {
                "1.0": 0.8813,
                "1.1": 0.3849,
                "1.2": 0.0488,
                "1.3": 0.0017
            },
            "threshold": {
                "0.50": 1.0795,
                "0.75": 1.1273,
                "0.90": 1.1719,
                "0.99": 1.2518
            },
            "price": 12474
        },
        "2014-06-22": {
            "ratio": {
                "1.0": 0.9217,
                "1.1": 0.4595,
                "1.2": 0.0665,
                "1.3": 0.0025
            },
            "threshold": {
                "0.50": 1.0931,
                "0.75": 1.14,
                "0.90": 1.1838,
                "0.99": 1.2625
            },
            "price": 12545
        },
        "2014-06-29": {
            "ratio": {
                "1.0": 0.9436,
                "1.1": 0.51,
                "1.2": 0.0785,
                "1.3": 0.0029
            },
            "threshold": {
                "0.50": 1.1018,
                "0.75": 1.1476,
                "0.90": 1.1904,
                "0.99": 1.2673
            },
            "price": 12535
        },
        "2014-07-06": {
            "ratio": {
                "1.0": 0.9213,
                "1.1": 0.4204,
                "1.2": 0.0442,
                "1.3": 0.0009
            },
            "threshold": {
                "0.50": 1.0872,
                "0.75": 1.1308,
                "0.90": 1.1713,
                "0.99": 1.2435
            },
            "price": 12622
        },
        "2014-07-13": {
            "ratio": {
                "1.0": 0.9071,
                "1.1": 0.3828,
                "1.2": 0.0356,
                "1.3": 0.0007
            },
            "threshold": {
                "0.50": 1.081,
                "0.75": 1.1243,
                "0.90": 1.1645,
                "0.99": 1.2364
            },
            "price": 12573
        },
        "2014-07-20": {
            "ratio": {
                "1.0": 0.871,
                "1.1": 0.3031,
                "1.2": 0.0206,
                "1.3": 0.0003
            },
            "threshold": {
                "0.50": 1.0679,
                "0.75": 1.1102,
                "0.90": 1.1494,
                "0.99": 1.2196
            },
            "price": 12549
        },
        "2014-07-27": {
            "ratio": {
                "1.0": 0.8658,
                "1.1": 0.2916,
                "1.2": 0.0187,
                "1.3": 0.0002
            },
            "threshold": {
                "0.50": 1.066,
                "0.75": 1.1079,
                "0.90": 1.1469,
                "0.99": 1.2166
            },
            "price": 12650
        },
        "2014-08-03": {
            "ratio": {
                "1.0": 0.9097,
                "1.1": 0.3624,
                "1.2": 0.0276,
                "1.3": 0.0004
            },
            "threshold": {
                "0.50": 1.0785,
                "0.75": 1.1201,
                "0.90": 1.1586,
                "0.99": 1.2275
            },
            "price": 12561
        },
        "2014-08-10": {
            "ratio": {
                "1.0": 0.9056,
                "1.1": 0.3515,
                "1.2": 0.0258,
                "1.3": 0.0003
            },
            "threshold": {
                "0.50": 1.0768,
                "0.75": 1.1182,
                "0.90": 1.1566,
                "0.99": 1.2254
            },
            "price": 12484
        },
        "2014-08-17": {
            "ratio": {
                "1.0": 0.9195,
                "1.1": 0.3795,
                "1.2": 0.0298,
                "1.3": 0.0004
            },
            "threshold": {
                "0.50": 1.0814,
                "0.75": 1.1227,
                "0.90": 1.1609,
                "0.99": 1.2295
            },
            "price": 12628
        },
        "2014-08-24": {
            "ratio": {
                "1.0": 0.9551,
                "1.1": 0.4874,
                "1.2": 0.0517,
                "1.3": 0.0009
            },
            "threshold": {
                "0.50": 1.0981,
                "0.75": 1.1394,
                "0.90": 1.1776,
                "0.99": 1.2461
            },
            "price": 12715
        },
        "2014-08-31": {
            "ratio": {
                "1.0": 0.9655,
                "1.1": 0.5355,
                "1.2": 0.065,
                "1.3": 0.0013
            },
            "threshold": {
                "0.50": 1.1054,
                "0.75": 1.1467,
                "0.90": 1.1851,
                "0.99": 1.2535
            },
            "price": 12739
        },
        "2014-09-07": {
            "ratio": {
                "1.0": 0.9663,
                "1.1": 0.5311,
                "1.2": 0.0608,
                "1.3": 0.0011
            },
            "threshold": {
                "0.50": 1.1047,
                "0.75": 1.1455,
                "0.90": 1.1832,
                "0.99": 1.2504
            },
            "price": 12815
        },
        "2014-09-14": {
            "ratio": {
                "1.0": 0.9476,
                "1.1": 0.4256,
                "1.2": 0.0303,
                "1.3": 0.0003
            },
            "threshold": {
                "0.50": 1.0894,
                "0.75": 1.1282,
                "0.90": 1.164,
                "0.99": 1.2279
            },
            "price": 12789
        },
        "2014-09-21": {
            "ratio": {
                "1.0": 0.9163,
                "1.1": 0.3178,
                "1.2": 0.0135,
                "1.3": 0.0001
            },
            "threshold": {
                "0.50": 1.0738,
                "0.75": 1.1113,
                "0.90": 1.1458,
                "0.99": 1.207
            },
            "price": 12787
        },
        "2014-09-28": {
            "ratio": {
                "1.0": 0.9086,
                "1.1": 0.2818,
                "1.2": 0.0087,
                "1.3": 0
            },
            "threshold": {
                "0.50": 1.0692,
                "0.75": 1.1053,
                "0.90": 1.1385,
                "0.99": 1.197
            },
            "price": 12693
        },
        "2014-10-05": {
            "ratio": {
                "1.0": 0.9259,
                "1.1": 0.3084,
                "1.2": 0.0099,
                "1.3": 0
            },
            "threshold": {
                "0.50": 1.0737,
                "0.75": 1.1093,
                "0.90": 1.142,
                "0.99": 1.1999
            },
            "price": 12617
        },
        "2014-10-12": {
            "ratio": {
                "1.0": 0.9211,
                "1.1": 0.2931,
                "1.2": 0.0086,
                "1.3": 0
            },
            "threshold": {
                "0.50": 1.0715,
                "0.75": 1.1069,
                "0.90": 1.1394,
                "0.99": 1.197
            },
            "price": 12612
        },
        "2014-10-19": {
            "ratio": {
                "1.0": 0.8448,
                "1.1": 0.1664,
                "1.2": 0.0023,
                "1.3": 0
            },
            "threshold": {
                "0.50": 1.0504,
                "0.75": 1.0848,
                "0.90": 1.1164,
                "0.99": 1.1722
            },
            "price": 12479
        },
        "2014-10-26": {
            "ratio": {
                "1.0": 0.8362,
                "1.1": 0.1586,
                "1.2": 0.0021,
                "1.3": 0
            },
            "threshold": {
                "0.50": 1.0488,
                "0.75": 1.0832,
                "0.90": 1.1147,
                "0.99": 1.1706
            },
            "price": 12634
        },
        "2014-11-02": {
            "ratio": {
                "1.0": 0.8753,
                "1.1": 0.2143,
                "1.2": 0.0043,
                "1.3": 0
            },
            "threshold": {
                "0.50": 1.0585,
                "0.75": 1.0938,
                "0.90": 1.1263,
                "0.99": 1.1833
            },
            "price": 12771
        },
        "2014-11-09": {
            "ratio": {
                "1.0": 0.9395,
                "1.1": 0.3745,
                "1.2": 0.0198,
                "1.3": 0.0001
            },
            "threshold": {
                "0.50": 1.0824,
                "0.75": 1.1199,
                "0.90": 1.1544,
                "0.99": 1.2162
            },
            "price": 12960
        },
        "2014-11-16": {
            "ratio": {
                "1.0": 0.9595,
                "1.1": 0.4458,
                "1.2": 0.0296,
                "1.3": 0.0002
            },
            "threshold": {
                "0.50": 1.0925,
                "0.75": 1.13,
                "0.90": 1.1646,
                "0.99": 1.2263
            },
            "price": 13033
        },
        "2014-11-23": {
            "ratio": {
                "1.0": 0.9605,
                "1.1": 0.4496,
                "1.2": 0.0299,
                "1.3": 0.0002
            },
            "threshold": {
                "0.50": 1.0931,
                "0.75": 1.1305,
                "0.90": 1.165,
                "0.99": 1.2264
            },
            "price": 13197
        },
        "2014-11-30": {
            "ratio": {
                "1.0": 0.9668,
                "1.1": 0.4885,
                "1.2": 0.0384,
                "1.3": 0.0003
            },
            "threshold": {
                "0.50": 1.0984,
                "0.75": 1.1363,
                "0.90": 1.1713,
                "0.99": 1.2336
            },
            "price": 13300
        },
        "2014-12-07": {
            "ratio": {
                "1.0": 0.9703,
                "1.1": 0.5038,
                "1.2": 0.0408,
                "1.3": 0.0004
            },
            "threshold": {
                "0.50": 1.1005,
                "0.75": 1.1383,
                "0.90": 1.173,
                "0.99": 1.235
            },
            "price": 13297
        },
        "2014-12-14": {
            "ratio": {
                "1.0": 0.9575,
                "1.1": 0.4482,
                "1.2": 0.0314,
                "1.3": 0.0003
            },
            "threshold": {
                "0.50": 1.0928,
                "0.75": 1.1308,
                "0.90": 1.1658,
                "0.99": 1.2283
            },
            "price": 13131
        },
        "2014-12-21": {
            "ratio": {
                "1.0": 0.92,
                "1.1": 0.3604,
                "1.2": 0.0214,
                "1.3": 0.0002
            },
            "threshold": {
                "0.50": 1.0793,
                "0.75": 1.1186,
                "0.90": 1.1548,
                "0.99": 1.2186
            },
            "price": 13145
        },
        "2014-12-28": {
            "ratio": {
                "1.0": 0.9286,
                "1.1": 0.3962,
                "1.2": 0.0296,
                "1.3": 0.0003
            },
            "threshold": {
                "0.50": 1.0844,
                "0.75": 1.1248,
                "0.90": 1.162,
                "0.99": 1.2283
            },
            "price": 13224
        },
        "2015-01-04": {
            "ratio": {
                "1.0": 0.9215,
                "1.1": 0.3732,
                "1.2": 0.0253,
                "1.3": 0.0003
            },
            "threshold": {
                "0.50": 1.081,
                "0.75": 1.121,
                "0.90": 1.158,
                "0.99": 1.2238
            },
            "price": 13242
        },
        "2015-01-11": {
            "ratio": {
                "1.0": 0.9314,
                "1.1": 0.3974,
                "1.2": 0.0286,
                "1.3": 0.0003
            },
            "threshold": {
                "0.50": 1.0848,
                "0.75": 1.1247,
                "0.90": 1.1615,
                "0.99": 1.227
            },
            "price": 13273
        },
        "2015-01-18": {
            "ratio": {
                "1.0": 0.9303,
                "1.1": 0.3957,
                "1.2": 0.0286,
                "1.3": 0.0003
            },
            "threshold": {
                "0.50": 1.0845,
                "0.75": 1.1245,
                "0.90": 1.1614,
                "0.99": 1.227
            },
            "price": 13171
        },
        "2015-01-25": {
            "ratio": {
                "1.0": 0.9443,
                "1.1": 0.4502,
                "1.2": 0.0409,
                "1.3": 0.0006
            },
            "threshold": {
                "0.50": 1.0925,
                "0.75": 1.1334,
                "0.90": 1.1709,
                "0.99": 1.2379
            },
            "price": 13367
        },
        "2015-02-01": {
            "ratio": {
                "1.0": 0.9735,
                "1.1": 0.5613,
                "1.2": 0.0651,
                "1.3": 0.0011
            },
            "threshold": {
                "0.50": 1.109,
                "0.75": 1.1489,
                "0.90": 1.1858,
                "0.99": 1.2514
            },
            "price": 13272
        },
        "2015-02-08": {
            "ratio": {
                "1.0": 0.976,
                "1.1": 0.5735,
                "1.2": 0.0679,
                "1.3": 0.0011
            },
            "threshold": {
                "0.50": 1.1107,
                "0.75": 1.1504,
                "0.90": 1.1871,
                "0.99": 1.2526
            },
            "price": 13261
        }
    }
}