{
    "modified": 1424359812,
    "modified_str": "2015-02-19 15:30:12",
    "stability": {
        "2007-03-18": {
            "period": {
                "4": 0.1939589,
                "13": 0.72582801,
                "26": 0.91941724,
                "52": 0.93992706
            },
            "price": 12333
        },
        "2007-03-25": {
            "period": {
                "4": 0.20194548,
                "13": 0.75851043,
                "26": 0.91456874,
                "52": 0.93690309
            },
            "price": 12615
        },
        "2007-04-01": {
            "period": {
                "4": 0.33258603,
                "13": 0.73348872,
                "26": 0.90741828,
                "52": 0.93304803
            },
            "price": 12319
        },
        "2007-04-08": {
            "period": {
                "4": 0.68120868,
                "13": 0.71662705,
                "26": 0.88663798,
                "52": 0.93910386
            },
            "price": 12586
        },
        "2007-04-15": {
            "period": {
                "4": 0.67143248,
                "13": 0.73812217,
                "26": 0.86840248,
                "52": 0.96024545
            },
            "price": 12449
        },
        "2007-04-22": {
            "period": {
                "4": 0.50404779,
                "13": 0.63871884,
                "26": 0.8438103,
                "52": 0.96074571
            },
            "price": 12410
        },
        "2007-04-29": {
            "period": {
                "4": 0.5796413,
                "13": 0.57816919,
                "26": 0.83722601,
                "52": 0.96055637
            },
            "price": 12495
        },
        "2007-05-06": {
            "period": {
                "4": 0.27021619,
                "13": 0.44551281,
                "26": 0.80771875,
                "52": 0.95662105
            },
            "price": 12307
        },
        "2007-05-13": {
            "period": {
                "4": 0.31685365,
                "13": 0.32261489,
                "26": 0.85261527,
                "52": 0.95514489
            },
            "price": 12423
        },
        "2007-05-20": {
            "period": {
                "4": 0.27891211,
                "13": 0.21937081,
                "26": 0.79629841,
                "52": 0.96266746
            },
            "price": 12084
        },
        "2007-05-27": {
            "period": {
                "4": 0.08690064,
                "13": 0.1222437,
                "26": 0.62958391,
                "52": 0.96460492
            },
            "price": 11892
        },
        "2007-06-03": {
            "period": {
                "4": 0.26134293,
                "13": 0.23135102,
                "26": 0.60829313,
                "52": 0.96062284
            },
            "price": 12368
        },
        "2007-06-10": {
            "period": {
                "4": 0.33257627,
                "13": 0.45067253,
                "26": 0.62969152,
                "52": 0.95261895
            },
            "price": 11879
        },
        "2007-06-17": {
            "period": {
                "4": 0.2593955,
                "13": 0.2781258,
                "26": 0.51863296,
                "52": 0.92671078
            },
            "price": 11840
        },
        "2007-06-24": {
            "period": {
                "4": 0.35025608,
                "13": 0.21407831,
                "26": 0.50722055,
                "52": 0.92325471
            },
            "price": 11630
        },
        "2007-07-01": {
            "period": {
                "4": 0.17326114,
                "13": 0.14261839,
                "26": 0.41801206,
                "52": 0.88535078
            },
            "price": 11501
        },
        "2007-07-08": {
            "period": {
                "4": 0.09230041,
                "13": 0.13714515,
                "26": 0.40462619,
                "52": 0.85763908
            },
            "price": 11688
        },
        "2007-07-15": {
            "period": {
                "4": 0.23224698,
                "13": 0.12018442,
                "26": 0.40508684,
                "52": 0.83795316
            },
            "price": 11508
        },
        "2007-07-22": {
            "period": {
                "4": 0.22583364,
                "13": 0.12487423,
                "26": 0.32048177,
                "52": 0.83376867
            },
            "price": 11506
        },
        "2007-07-29": {
            "period": {
                "4": 0.21800812,
                "13": 0.06644919,
                "26": 0.19013687,
                "52": 0.7381212
            },
            "price": 10807
        },
        "2007-08-05": {
            "period": {
                "4": 0.03311934,
                "13": 0.04347425,
                "26": 0.09441176,
                "52": 0.59337064
            },
            "price": 10719
        },
        "2007-08-12": {
            "period": {
                "4": 0.12544578,
                "13": 0.06103821,
                "26": 0.06869742,
                "52": 0.62857131
            },
            "price": 11083
        },
        "2007-08-19": {
            "period": {
                "4": 0.13897367,
                "13": 0.07193184,
                "26": 0.05017311,
                "52": 0.56728892
            },
            "price": 10413
        },
        "2007-08-26": {
            "period": {
                "4": 0.35943845,
                "13": 0.15820784,
                "26": 0.06746087,
                "52": 0.57143071
            },
            "price": 11009
        },
        "2007-09-02": {
            "period": {
                "4": 0.63230815,
                "13": 0.17656954,
                "26": 0.11849847,
                "52": 0.58332262
            },
            "price": 10927
        },
        "2007-09-09": {
            "period": {
                "4": 0.6260575,
                "13": 0.17665087,
                "26": 0.20498814,
                "52": 0.59348239
            },
            "price": 11059
        },
        "2007-09-16": {
            "period": {
                "4": 0.6381358,
                "13": 0.20809344,
                "26": 0.15857989,
                "52": 0.53535653
            },
            "price": 10965
        },
        "2007-09-23": {
            "period": {
                "4": 0.70913812,
                "13": 0.27544579,
                "26": 0.17254226,
                "52": 0.54736723
            },
            "price": 11163
        },
        "2007-09-30": {
            "period": {
                "4": 0.78161931,
                "13": 0.41341583,
                "26": 0.21212213,
                "52": 0.58517254
            },
            "price": 11319
        },
        "2007-10-07": {
            "period": {
                "4": 0.83056214,
                "13": 0.46272187,
                "26": 0.24304578,
                "52": 0.58590069
            },
            "price": 11524
        },
        "2007-10-14": {
            "period": {
                "4": 0.99903361,
                "13": 0.51287753,
                "26": 0.26089986,
                "52": 0.57862764
            },
            "price": 11587
        },
        "2007-10-21": {
            "period": {
                "4": 0.77581444,
                "13": 0.45949955,
                "26": 0.23281266,
                "52": 0.52140941
            },
            "price": 11229
        },
        "2007-10-28": {
            "period": {
                "4": 0.3982862,
                "13": 0.49417362,
                "26": 0.17952462,
                "52": 0.45313679
            },
            "price": 11116
        },
        "2007-11-04": {
            "period": {
                "4": 0.22525771,
                "13": 0.66938139,
                "26": 0.20908018,
                "52": 0.45976443
            },
            "price": 11040
        },
        "2007-11-11": {
            "period": {
                "4": 0.02795547,
                "13": 0.46056484,
                "26": 0.1355959,
                "52": 0.40536029
            },
            "price": 10519
        },
        "2007-11-18": {
            "period": {
                "4": 0.0379025,
                "13": 0.45726792,
                "26": 0.13288277,
                "52": 0.3516748
            },
            "price": 10531
        },
        "2007-11-25": {
            "period": {
                "4": 0.0406699,
                "13": 0.28983715,
                "26": 0.12898947,
                "52": 0.23706411
            },
            "price": 10174
        },
        "2007-12-02": {
            "period": {
                "4": 0.03284927,
                "13": 0.22483904,
                "26": 0.11416224,
                "52": 0.21076215
            },
            "price": 10360
        },
        "2007-12-09": {
            "period": {
                "4": 0.33226715,
                "13": 0.26492548,
                "26": 0.12986349,
                "52": 0.25068672
            },
            "price": 10655
        },
        "2007-12-16": {
            "period": {
                "4": 0.50370614,
                "13": 0.35524345,
                "26": 0.19173065,
                "52": 0.26081542
            },
            "price": 10323
        },
        "2007-12-23": {
            "period": {
                "4": 0.35509456,
                "13": 0.14641801,
                "26": 0.1222601,
                "52": 0.18340665
            },
            "price": 9936
        },
        "2007-12-30": {
            "period": {
                "4": 0.44784237,
                "13": 0.15091114,
                "26": 0.18776008,
                "52": 0.20296005
            },
            "price": 10057
        },
        "2008-01-06": {
            "period": {
                "4": 0.25275927,
                "13": 0.08250496,
                "26": 0.15507852,
                "52": 0.17046703
            },
            "price": 9804
        },
        "2008-01-13": {
            "period": {
                "4": 0.08112668,
                "13": 0.02949663,
                "26": 0.10009992,
                "52": 0.12173453
            },
            "price": 9448
        },
        "2008-01-20": {
            "period": {
                "4": 0.13938366,
                "13": 0.02968831,
                "26": 0.08759816,
                "52": 0.08577971
            },
            "price": 9285
        },
        "2008-01-27": {
            "period": {
                "4": 0.07928174,
                "13": 0.05748011,
                "26": 0.12980898,
                "52": 0.07558761
            },
            "price": 9625
        },
        "2008-02-03": {
            "period": {
                "4": 0.34882601,
                "13": 0.12907275,
                "26": 0.26985755,
                "52": 0.09728173
            },
            "price": 9761
        },
        "2008-02-10": {
            "period": {
                "4": 0.62011109,
                "13": 0.20209679,
                "26": 0.24143306,
                "52": 0.07165079
            },
            "price": 9566
        },
        "2008-02-17": {
            "period": {
                "4": 0.60259072,
                "13": 0.19168767,
                "26": 0.22707954,
                "52": 0.05321289
            },
            "price": 9499
        },
        "2008-02-24": {
            "period": {
                "4": 0.57302947,
                "13": 0.24696574,
                "26": 0.18800035,
                "52": 0.04808108
            },
            "price": 9476
        },
        "2008-03-02": {
            "period": {
                "4": 0.41123978,
                "13": 0.28596221,
                "26": 0.18127166,
                "52": 0.06991282
            },
            "price": 9589
        },
        "2008-03-09": {
            "period": {
                "4": 0.20709307,
                "13": 0.16401286,
                "26": 0.1213415,
                "52": 0.07765725
            },
            "price": 9255
        },
        "2008-03-16": {
            "period": {
                "4": 0.21118479,
                "13": 0.11725709,
                "26": 0.11988418,
                "52": 0.06122503
            },
            "price": 9250
        },
        "2008-03-23": {
            "period": {
                "4": 0.30333552,
                "13": 0.23972489,
                "26": 0.10747912,
                "52": 0.06008199
            },
            "price": 9436
        },
        "2008-03-30": {
            "period": {
                "4": 0.45096444,
                "13": 0.28240797,
                "26": 0.12741848,
                "52": 0.08320333
            },
            "price": 9572
        },
        "2008-04-06": {
            "period": {
                "4": 0.83597655,
                "13": 0.42221249,
                "26": 0.13864833,
                "52": 0.10062404
            },
            "price": 10007
        },
        "2008-04-13": {
            "period": {
                "4": 0.91398278,
                "13": 0.6270652,
                "26": 0.13391222,
                "52": 0.1038731
            },
            "price": 9675
        },
        "2008-04-20": {
            "period": {
                "4": 0.78106128,
                "13": 0.64796314,
                "26": 0.14657821,
                "52": 0.10124874
            },
            "price": 9845
        },
        "2008-04-27": {
            "period": {
                "4": 0.71863937,
                "13": 0.69804638,
                "26": 0.21148816,
                "52": 0.11291748
            },
            "price": 9888
        },
        "2008-05-04": {
            "period": {
                "4": 0.63131247,
                "13": 0.60674391,
                "26": 0.22418578,
                "52": 0.13382282
            },
            "price": 9971
        },
        "2008-05-11": {
            "period": {
                "4": 0.64894347,
                "13": 0.60675695,
                "26": 0.30076322,
                "52": 0.12760419
            },
            "price": 9866
        },
        "2008-05-18": {
            "period": {
                "4": 0.82185645,
                "13": 0.704159,
                "26": 0.33408669,
                "52": 0.13959122
            },
            "price": 10003
        },
        "2008-05-25": {
            "period": {
                "4": 0.50634013,
                "13": 0.66791691,
                "26": 0.3767768,
                "52": 0.15453816
            },
            "price": 9685
        },
        "2008-06-01": {
            "period": {
                "4": 0.21986282,
                "13": 0.54356884,
                "26": 0.34536832,
                "52": 0.13033049
            },
            "price": 9744
        },
        "2008-06-08": {
            "period": {
                "4": 0.23961696,
                "13": 0.67782845,
                "26": 0.29143426,
                "52": 0.11888701
            },
            "price": 9801
        },
        "2008-06-15": {
            "period": {
                "4": 0.10880558,
                "13": 0.62520706,
                "26": 0.22024747,
                "52": 0.1220687
            },
            "price": 9307
        },
        "2008-06-22": {
            "period": {
                "4": 0.09674843,
                "13": 0.53583319,
                "26": 0.31211034,
                "52": 0.11741033
            },
            "price": 9318
        },
        "2008-06-29": {
            "period": {
                "4": 0.05319073,
                "13": 0.28258232,
                "26": 0.2089352,
                "52": 0.1141589
            },
            "price": 8964
        },
        "2008-07-06": {
            "period": {
                "4": 0.00300656,
                "13": 0.08817544,
                "26": 0.16544472,
                "52": 0.07950082
            },
            "price": 8699
        },
        "2008-07-13": {
            "period": {
                "4": 0.0011177,
                "13": 0.03222403,
                "26": 0.21170786,
                "52": 0.06749505
            },
            "price": 8526
        },
        "2008-07-20": {
            "period": {
                "4": 0.00030098,
                "13": 0.02126186,
                "26": 0.20073551,
                "52": 0.05759264
            },
            "price": 8559
        },
        "2008-07-27": {
            "period": {
                "4": 0.28846867,
                "13": 0.10650135,
                "26": 0.31018234,
                "52": 0.12228061
            },
            "price": 8845
        },
        "2008-08-03": {
            "period": {
                "4": 0.47435151,
                "13": 0.09539012,
                "26": 0.2152557,
                "52": 0.16471207
            },
            "price": 8819
        },
        "2008-08-10": {
            "period": {
                "4": 0.67650035,
                "13": 0.1151242,
                "26": 0.23455132,
                "52": 0.15822282
            },
            "price": 8886
        },
        "2008-08-17": {
            "period": {
                "4": 0.94442583,
                "13": 0.15674788,
                "26": 0.32637548,
                "52": 0.19478271
            },
            "price": 8955
        },
        "2008-08-24": {
            "period": {
                "4": 0.53596321,
                "13": 0.12916493,
                "26": 0.2747858,
                "52": 0.14542314
            },
            "price": 8672
        },
        "2008-08-31": {
            "period": {
                "4": 0.54058693,
                "13": 0.17207127,
                "26": 0.25623793,
                "52": 0.13320253
            },
            "price": 8975
        },
        "2008-09-07": {
            "period": {
                "4": 0.57942654,
                "13": 0.21415742,
                "26": 0.3605132,
                "52": 0.13622372
            },
            "price": 8875
        },
        "2008-09-14": {
            "period": {
                "4": 0.4857465,
                "13": 0.29821905,
                "26": 0.41759042,
                "52": 0.15743372
            },
            "price": 9024
        },
        "2008-09-21": {
            "period": {
                "4": 0.55913877,
                "13": 0.2876556,
                "26": 0.35332758,
                "52": 0.12366137
            },
            "price": 8940
        },
        "2008-09-28": {
            "period": {
                "4": 0.59056611,
                "13": 0.41758765,
                "26": 0.30219699,
                "52": 0.11816112
            },
            "price": 8839
        },
        "2008-10-05": {
            "period": {
                "4": 0.24631013,
                "13": 0.43271458,
                "26": 0.17197285,
                "52": 0.07526045
            },
            "price": 8454
        },
        "2008-10-12": {
            "period": {
                "4": 0.06579453,
                "13": 0.2568569,
                "26": 0.0723607,
                "52": 0.03435183
            },
            "price": 7327
        },
        "2008-10-19": {
            "period": {
                "4": 0.03169415,
                "13": 0.20214187,
                "26": 0.04788936,
                "52": 0.02640736
            },
            "price": 7215
        },
        "2008-10-26": {
            "period": {
                "4": 0,
                "13": 0.06132362,
                "26": 0.02356878,
                "52": 0.02313742
            },
            "price": 6796
        },
        "2008-11-02": {
            "period": {
                "4": 0.00117139,
                "13": 0.03358323,
                "26": 0.01248241,
                "52": 0.0152361
            },
            "price": 6908
        },
        "2008-11-09": {
            "period": {
                "4": 0.16926053,
                "13": 0.0771903,
                "26": 0.0333885,
                "52": 0.03898907
            },
            "price": 6830
        },
        "2008-11-16": {
            "period": {
                "4": 0.18664749,
                "13": 0.03831033,
                "26": 0.02219243,
                "52": 0.03181215
            },
            "price": 6624
        },
        "2008-11-23": {
            "period": {
                "4": 0.13060313,
                "13": 0.02263421,
                "26": 0.01165383,
                "52": 0.02188575
            },
            "price": 5683
        },
        "2008-11-30": {
            "period": {
                "4": 0.28329667,
                "13": 0.04306612,
                "26": 0.02670513,
                "52": 0.03263292
            },
            "price": 6409
        },
        "2008-12-07": {
            "period": {
                "4": 0.21158339,
                "13": 0.04880279,
                "26": 0.0352006,
                "52": 0.03309521
            },
            "price": 6098
        },
        "2008-12-14": {
            "period": {
                "4": 0.38292476,
                "13": 0.07111747,
                "26": 0.06263147,
                "52": 0.04354626
            },
            "price": 6227
        },
        "2008-12-21": {
            "period": {
                "4": 0.66461403,
                "13": 0.09317982,
                "26": 0.07829854,
                "52": 0.06966838
            },
            "price": 6475
        },
        "2008-12-28": {
            "period": {
                "4": 0.73200294,
                "13": 0.09401523,
                "26": 0.10228269,
                "52": 0.06764715
            },
            "price": 6513
        },
        "2009-01-04": {
            "period": {
                "4": 0.73465971,
                "13": 0.10723366,
                "26": 0.1176626,
                "52": 0.06707893
            },
            "price": 6412
        },
        "2009-01-11": {
            "period": {
                "4": 0.76622046,
                "13": 0.21930363,
                "26": 0.15407015,
                "52": 0.1032103
            },
            "price": 6584
        },
        "2009-01-18": {
            "period": {
                "4": 0.38269699,
                "13": 0.23670787,
                "26": 0.1399485,
                "52": 0.09060373
            },
            "price": 6115
        },
        "2009-01-25": {
            "period": {
                "4": 0.18155358,
                "13": 0.24866749,
                "26": 0.08240327,
                "52": 0.07364901
            },
            "price": 6056
        },
        "2009-02-01": {
            "period": {
                "4": 0.28705162,
                "13": 0.33732502,
                "26": 0.08658828,
                "52": 0.058886
            },
            "price": 6162
        },
        "2009-02-08": {
            "period": {
                "4": 0.10634404,
                "13": 0.22627964,
                "26": 0.06976735,
                "52": 0.05082219
            },
            "price": 5890
        },
        "2009-02-15": {
            "period": {
                "4": 0.24008226,
                "13": 0.29884191,
                "26": 0.06287761,
                "52": 0.05920703
            },
            "price": 5919
        },
        "2009-02-22": {
            "period": {
                "4": 0.16513953,
                "13": 0.33362206,
                "26": 0.0488904,
                "52": 0.04112454
            },
            "price": 5460
        },
        "2009-03-01": {
            "period": {
                "4": 0.05175578,
                "13": 0.22952125,
                "26": 0.03710418,
                "52": 0.03033367
            },
            "price": 5439
        },
        "2009-03-08": {
            "period": {
                "4": 0.02658886,
                "13": 0.13785796,
                "26": 0.02435183,
                "52": 0.02830697
            },
            "price": 5129
        },
        "2009-03-15": {
            "period": {
                "4": 0.0768381,
                "13": 0.09159548,
                "26": 0.02648797,
                "52": 0.03461489
            },
            "price": 5523
        },
        "2009-03-22": {
            "period": {
                "4": 0.43976305,
                "13": 0.164568,
                "26": 0.05101995,
                "52": 0.05183252
            },
            "price": 5654
        },
        "2009-03-29": {
            "period": {
                "4": 0.5853632,
                "13": 0.14968693,
                "26": 0.04807486,
                "52": 0.04338758
            },
            "price": 5650
        },
        "2009-04-05": {
            "period": {
                "4": 0.74617022,
                "13": 0.17207318,
                "26": 0.06003997,
                "52": 0.0358304
            },
            "price": 5720
        },
        "2009-04-12": {
            "period": {
                "4": 0.92901883,
                "13": 0.23786831,
                "26": 0.14767773,
                "52": 0.05207001
            },
            "price": 6056
        },
        "2009-04-19": {
            "period": {
                "4": 0.91696656,
                "13": 0.41527808,
                "26": 0.24088224,
                "52": 0.07205854
            },
            "price": 6180
        },
        "2009-04-26": {
            "period": {
                "4": 0.93232312,
                "13": 0.50953588,
                "26": 0.29546199,
                "52": 0.0685813
            },
            "price": 6114
        },
        "2009-05-03": {
            "period": {
                "4": 0.97751425,
                "13": 0.51269546,
                "26": 0.3743221,
                "52": 0.0686542
            },
            "price": 6231
        },
        "2009-05-10": {
            "period": {
                "4": 0.95546452,
                "13": 0.61079325,
                "26": 0.33425826,
                "52": 0.07566336
            },
            "price": 6251
        },
        "2009-05-17": {
            "period": {
                "4": 0.69551587,
                "13": 0.58020955,
                "26": 0.38564055,
                "52": 0.07266821
            },
            "price": 6084
        },
        "2009-05-24": {
            "period": {
                "4": 0.54518788,
                "13": 0.72300404,
                "26": 0.5052558,
                "52": 0.07095138
            },
            "price": 6124
        },
        "2009-05-31": {
            "period": {
                "4": 0.55784211,
                "13": 0.83691372,
                "26": 0.51593682,
                "52": 0.08205285
            },
            "price": 6247
        },
        "2009-06-07": {
            "period": {
                "4": 0.68728199,
                "13": 0.94958792,
                "26": 0.58835474,
                "52": 0.10456824
            },
            "price": 6533
        },
        "2009-06-14": {
            "period": {
                "4": 0.75866013,
                "13": 0.96550019,
                "26": 0.53237074,
                "52": 0.12047883
            },
            "price": 6360
        },
        "2009-06-21": {
            "period": {
                "4": 0.70849386,
                "13": 0.88530547,
                "26": 0.45453013,
                "52": 0.11434294
            },
            "price": 6239
        },
        "2009-06-28": {
            "period": {
                "4": 0.52320322,
                "13": 0.85221907,
                "26": 0.40397459,
                "52": 0.12193503
            },
            "price": 6280
        },
        "2009-07-05": {
            "period": {
                "4": 0.30506169,
                "13": 0.88600035,
                "26": 0.45692443,
                "52": 0.15423117
            },
            "price": 6240
        },
        "2009-07-12": {
            "period": {
                "4": 0.14298892,
                "13": 0.71113939,
                "26": 0.37020792,
                "52": 0.15372698
            },
            "price": 6085
        },
        "2009-07-19": {
            "period": {
                "4": 0.40095435,
                "13": 0.6143657,
                "26": 0.48488769,
                "52": 0.18219994
            },
            "price": 6391
        },
        "2009-07-26": {
            "period": {
                "4": 0.73399755,
                "13": 0.71281085,
                "26": 0.62351365,
                "52": 0.1719154
            },
            "price": 6526
        },
        "2009-08-02": {
            "period": {
                "4": 0.78172506,
                "13": 0.74831767,
                "26": 0.64769727,
                "52": 0.18636458
            },
            "price": 6650
        },
        "2009-08-09": {
            "period": {
                "4": 0.97972036,
                "13": 0.81153036,
                "26": 0.76610075,
                "52": 0.21827279
            },
            "price": 7052
        },
        "2009-08-16": {
            "period": {
                "4": 1,
                "13": 0.90596049,
                "26": 0.81585837,
                "52": 0.24095897
            },
            "price": 7111
        },
        "2009-08-23": {
            "period": {
                "4": 0.92633929,
                "13": 0.90953951,
                "26": 0.89770196,
                "52": 0.24698921
            },
            "price": 7032
        },
        "2009-08-30": {
            "period": {
                "4": 0.923035,
                "13": 0.92535597,
                "26": 0.95261174,
                "52": 0.26831876
            },
            "price": 7276
        },
        "2009-09-06": {
            "period": {
                "4": 0.74365336,
                "13": 0.84731672,
                "26": 0.97254344,
                "52": 0.25081766
            },
            "price": 7073
        },
        "2009-09-13": {
            "period": {
                "4": 0.62351299,
                "13": 0.8717811,
                "26": 0.98229394,
                "52": 0.26361999
            },
            "price": 7418
        },
        "2009-09-20": {
            "period": {
                "4": 0.90712203,
                "13": 0.9598098,
                "26": 0.98132866,
                "52": 0.32566933
            },
            "price": 7717
        },
        "2009-09-27": {
            "period": {
                "4": 0.85140632,
                "13": 0.9754025,
                "26": 0.98279269,
                "52": 0.32490253
            },
            "price": 7502
        },
        "2009-10-04": {
            "period": {
                "4": 0.773335,
                "13": 0.95038399,
                "26": 0.97856392,
                "52": 0.34224883
            },
            "price": 7428
        },
        "2009-10-11": {
            "period": {
                "4": 0.67312611,
                "13": 0.96600737,
                "26": 0.9553596,
                "52": 0.44684593
            },
            "price": 7563
        },
        "2009-10-18": {
            "period": {
                "4": 0.49167827,
                "13": 0.97393118,
                "26": 0.94288192,
                "52": 0.54224377
            },
            "price": 7613
        },
        "2009-10-25": {
            "period": {
                "4": 0.34646371,
                "13": 0.94574779,
                "26": 0.93589815,
                "52": 0.58913374
            },
            "price": 7536
        },
        "2009-11-01": {
            "period": {
                "4": 0.31409113,
                "13": 0.87273479,
                "26": 0.90116948,
                "52": 0.63134346
            },
            "price": 7342
        },
        "2009-11-08": {
            "period": {
                "4": 0.30031595,
                "13": 0.75231428,
                "26": 0.86921374,
                "52": 0.57059755
            },
            "price": 7347
        },
        "2009-11-15": {
            "period": {
                "4": 0.31174185,
                "13": 0.69368046,
                "26": 0.90868559,
                "52": 0.653324
            },
            "price": 7516
        },
        "2009-11-22": {
            "period": {
                "4": 0.52600479,
                "13": 0.80821229,
                "26": 0.94420265,
                "52": 0.79037919
            },
            "price": 7536
        },
        "2009-11-29": {
            "period": {
                "4": 0.63939342,
                "13": 0.68796646,
                "26": 0.9233089,
                "52": 0.79075398
            },
            "price": 7430
        },
        "2009-12-06": {
            "period": {
                "4": 0.75702181,
                "13": 0.7186236,
                "26": 0.88006556,
                "52": 0.79623957
            },
            "price": 7572
        },
        "2009-12-13": {
            "period": {
                "4": 0.62111653,
                "13": 0.68358278,
                "26": 0.88631229,
                "52": 0.76921428
            },
            "price": 7481
        },
        "2009-12-20": {
            "period": {
                "4": 0.45825144,
                "13": 0.47506558,
                "26": 0.9216524,
                "52": 0.75202608
            },
            "price": 7566
        },
        "2009-12-27": {
            "period": {
                "4": 0.77783183,
                "13": 0.52262612,
                "26": 0.9530805,
                "52": 0.75931048
            },
            "price": 7790
        },
        "2010-01-03": {
            "period": {
                "4": 0.89192329,
                "13": 0.71511575,
                "26": 0.95509171,
                "52": 0.79445325
            },
            "price": 7778
        },
        "2010-01-10": {
            "period": {
                "4": 0.87265235,
                "13": 0.74366333,
                "26": 0.97057798,
                "52": 0.76442678
            },
            "price": 7771
        },
        "2010-01-17": {
            "period": {
                "4": 0.84386877,
                "13": 0.65569243,
                "26": 0.9677948,
                "52": 0.82756618
            },
            "price": 7745
        },
        "2010-01-24": {
            "period": {
                "4": 0.55348846,
                "13": 0.65596308,
                "26": 0.94211833,
                "52": 0.86252087
            },
            "price": 7652
        },
        "2010-01-31": {
            "period": {
                "4": 0.05209093,
                "13": 0.64771213,
                "26": 0.8813115,
                "52": 0.83049483
            },
            "price": 7540
        },
        "2010-02-07": {
            "period": {
                "4": 0.10881046,
                "13": 0.69407196,
                "26": 0.8035599,
                "52": 0.85642423
            },
            "price": 7489
        },
        "2010-02-14": {
            "period": {
                "4": 0.04435652,
                "13": 0.47942686,
                "26": 0.65922325,
                "52": 0.8384118
            },
            "price": 7430
        },
        "2010-02-21": {
            "period": {
                "4": 0.21568812,
                "13": 0.45442171,
                "26": 0.75050506,
                "52": 0.92475358
            },
            "price": 7617
        },
        "2010-02-28": {
            "period": {
                "4": 0.64844889,
                "13": 0.64846345,
                "26": 0.73454823,
                "52": 0.95974766
            },
            "price": 7685
        },
        "2010-03-07": {
            "period": {
                "4": 0.78166161,
                "13": 0.70706165,
                "26": 0.78575183,
                "52": 0.97951694
            },
            "price": 7778
        },
        "2010-03-14": {
            "period": {
                "4": 0.99843164,
                "13": 0.80214717,
                "26": 0.81403256,
                "52": 0.98769607
            },
            "price": 7929
        },
        "2010-03-21": {
            "period": {
                "4": 1,
                "13": 0.85412959,
                "26": 0.73774926,
                "52": 0.98214331
            },
            "price": 8060
        },
        "2010-03-28": {
            "period": {
                "4": 0.99997885,
                "13": 0.82593988,
                "26": 0.74586828,
                "52": 0.98424285
            },
            "price": 8071
        },
        "2010-04-04": {
            "period": {
                "4": 0.98464507,
                "13": 0.75243706,
                "26": 0.80786374,
                "52": 0.98538471
            },
            "price": 8031
        },
        "2010-04-11": {
            "period": {
                "4": 0.94905118,
                "13": 0.80343171,
                "26": 0.85362307,
                "52": 0.9766862
            },
            "price": 8103
        },
        "2010-04-18": {
            "period": {
                "4": 0.94662055,
                "13": 0.85972789,
                "26": 0.84761083,
                "52": 0.96955121
            },
            "price": 8186
        },
        "2010-04-25": {
            "period": {
                "4": 0.80632907,
                "13": 0.87018953,
                "26": 0.85603556,
                "52": 0.96731204
            },
            "price": 8272
        },
        "2010-05-02": {
            "period": {
                "4": 0.92621727,
                "13": 0.97763504,
                "26": 0.94273004,
                "52": 0.96989363
            },
            "price": 8373
        },
        "2010-05-09": {
            "period": {
                "4": 0.73038903,
                "13": 0.95110686,
                "26": 0.93748818,
                "52": 0.95768445
            },
            "price": 8038
        },
        "2010-05-16": {
            "period": {
                "4": 0.49353134,
                "13": 0.9414793,
                "26": 0.87039633,
                "52": 0.9573497
            },
            "price": 8253
        },
        "2010-05-23": {
            "period": {
                "4": 0.34511825,
                "13": 0.7978375,
                "26": 0.72442968,
                "52": 0.94760477
            },
            "price": 7739
        },
        "2010-05-30": {
            "period": {
                "4": 0.15973976,
                "13": 0.62032465,
                "26": 0.67509552,
                "52": 0.91830259
            },
            "price": 7932
        },
        "2010-06-06": {
            "period": {
                "4": 0.27931396,
                "13": 0.63877239,
                "26": 0.7193733,
                "52": 0.89823086
            },
            "price": 7947
        },
        "2010-06-13": {
            "period": {
                "4": 0.24841537,
                "13": 0.48336732,
                "26": 0.66481755,
                "52": 0.8846435
            },
            "price": 7955
        },
        "2010-06-20": {
            "period": {
                "4": 0.59684279,
                "13": 0.55172386,
                "26": 0.74606366,
                "52": 0.93276297
            },
            "price": 8101
        },
        "2010-06-27": {
            "period": {
                "4": 0.70753072,
                "13": 0.47771548,
                "26": 0.66792561,
                "52": 0.93747101
            },
            "price": 7888
        },
        "2010-07-04": {
            "period": {
                "4": 0.37927394,
                "13": 0.38371254,
                "26": 0.5309488,
                "52": 0.9062217
            },
            "price": 7744
        },
        "2010-07-11": {
            "period": {
                "4": 0.39753456,
                "13": 0.31655432,
                "26": 0.50198306,
                "52": 0.91617324
            },
            "price": 7841
        },
        "2010-07-18": {
            "period": {
                "4": 0.33494019,
                "13": 0.36632104,
                "26": 0.58851369,
                "52": 0.92865274
            },
            "price": 7954
        },
        "2010-07-25": {
            "period": {
                "4": 0.46031764,
                "13": 0.39337989,
                "26": 0.62136989,
                "52": 0.9072305
            },
            "price": 8042
        },
        "2010-08-01": {
            "period": {
                "4": 0.85306903,
                "13": 0.42050147,
                "26": 0.75804489,
                "52": 0.90849171
            },
            "price": 8136
        },
        "2010-08-08": {
            "period": {
                "4": 0.99886766,
                "13": 0.4928794,
                "26": 0.78881067,
                "52": 0.87880519
            },
            "price": 8226
        },
        "2010-08-15": {
            "period": {
                "4": 0.83425363,
                "13": 0.49861202,
                "26": 0.80674324,
                "52": 0.81794187
            },
            "price": 8046
        },
        "2010-08-22": {
            "period": {
                "4": 0.68686062,
                "13": 0.57866393,
                "26": 0.75674045,
                "52": 0.83309337
            },
            "price": 8071
        },
        "2010-08-29": {
            "period": {
                "4": 0.35326264,
                "13": 0.67464275,
                "26": 0.69481894,
                "52": 0.7870152
            },
            "price": 8063
        },
        "2010-09-05": {
            "period": {
                "4": 0.47874909,
                "13": 0.6923192,
                "26": 0.71924009,
                "52": 0.83039781
            },
            "price": 8361
        },
        "2010-09-12": {
            "period": {
                "4": 0.77000631,
                "13": 0.82438754,
                "26": 0.71381645,
                "52": 0.84174629
            },
            "price": 8342
        },
        "2010-09-19": {
            "period": {
                "4": 0.88640475,
                "13": 0.72886634,
                "26": 0.67780251,
                "52": 0.77313447
            },
            "price": 8389
        },
        "2010-09-26": {
            "period": {
                "4": 0.93394679,
                "13": 0.78474506,
                "26": 0.65775296,
                "52": 0.76243716
            },
            "price": 8307
        },
        "2010-10-03": {
            "period": {
                "4": 0.74109258,
                "13": 0.87854233,
                "26": 0.649206,
                "52": 0.79175763
            },
            "price": 8382
        },
        "2010-10-10": {
            "period": {
                "4": 0.72851156,
                "13": 0.95512097,
                "26": 0.66448629,
                "52": 0.82735687
            },
            "price": 8514
        },
        "2010-10-17": {
            "period": {
                "4": 0.82288792,
                "13": 0.93466319,
                "26": 0.65343617,
                "52": 0.81686512
            },
            "price": 8558
        },
        "2010-10-24": {
            "period": {
                "4": 0.90416265,
                "13": 0.94009734,
                "26": 0.67991266,
                "52": 0.83732174
            },
            "price": 8618
        },
        "2010-10-31": {
            "period": {
                "4": 0.96352106,
                "13": 0.88593501,
                "26": 0.63210917,
                "52": 0.87596499
            },
            "price": 8556
        },
        "2010-11-07": {
            "period": {
                "4": 0.86162179,
                "13": 0.84389702,
                "26": 0.66647816,
                "52": 0.89127858
            },
            "price": 8695
        },
        "2010-11-14": {
            "period": {
                "4": 0.70126868,
                "13": 0.89774845,
                "26": 0.71252724,
                "52": 0.87117784
            },
            "price": 8540
        },
        "2010-11-21": {
            "period": {
                "4": 0.25402176,
                "13": 0.78365564,
                "26": 0.72211018,
                "52": 0.79500211
            },
            "price": 8370
        },
        "2010-11-28": {
            "period": {
                "4": 0.23789567,
                "13": 0.79515577,
                "26": 0.8044985,
                "52": 0.81392976
            },
            "price": 8444
        },
        "2010-12-05": {
            "period": {
                "4": 0.27628787,
                "13": 0.72715262,
                "26": 0.77431195,
                "52": 0.82098223
            },
            "price": 8512
        },
        "2010-12-12": {
            "period": {
                "4": 0.30397165,
                "13": 0.63778807,
                "26": 0.83252525,
                "52": 0.82402618
            },
            "price": 8434
        },
        "2010-12-19": {
            "period": {
                "4": 0.54666025,
                "13": 0.55600559,
                "26": 0.71738129,
                "52": 0.80666484
            },
            "price": 8384
        },
        "2010-12-26": {
            "period": {
                "4": 0.64574982,
                "13": 0.57521795,
                "26": 0.77120508,
                "52": 0.78226221
            },
            "price": 8508
        },
        "2011-01-02": {
            "period": {
                "4": 0.7475954,
                "13": 0.69664047,
                "26": 0.88918902,
                "52": 0.77415808
            },
            "price": 8582
        },
        "2011-01-09": {
            "period": {
                "4": 0.73267974,
                "13": 0.64320266,
                "26": 0.93286757,
                "52": 0.78964131
            },
            "price": 8545
        },
        "2011-01-16": {
            "period": {
                "4": 0.83601234,
                "13": 0.55069039,
                "26": 0.88330859,
                "52": 0.78743627
            },
            "price": 8599
        },
        "2011-01-23": {
            "period": {
                "4": 0.89011903,
                "13": 0.53617796,
                "26": 0.88375125,
                "52": 0.80752104
            },
            "price": 8581
        },
        "2011-01-30": {
            "period": {
                "4": 0.77831828,
                "13": 0.56974336,
                "26": 0.83583771,
                "52": 0.86030537
            },
            "price": 8711
        },
        "2011-02-06": {
            "period": {
                "4": 0.85527189,
                "13": 0.62093736,
                "26": 0.82527184,
                "52": 0.8746625
            },
            "price": 8739
        },
        "2011-02-13": {
            "period": {
                "4": 0.98164014,
                "13": 0.67045898,
                "26": 0.88680928,
                "52": 0.90769444
            },
            "price": 8767
        },
        "2011-02-20": {
            "period": {
                "4": 0.99205897,
                "13": 0.94879448,
                "26": 0.93098412,
                "52": 0.90211303
            },
            "price": 8831
        },
        "2011-02-27": {
            "period": {
                "4": 0.92209464,
                "13": 0.95493283,
                "26": 0.93544204,
                "52": 0.87562082
            },
            "price": 8727
        },
        "2011-03-06": {
            "period": {
                "4": 0.84012358,
                "13": 0.94098975,
                "26": 0.90461175,
                "52": 0.8631775
            },
            "price": 8839
        },
        "2011-03-13": {
            "period": {
                "4": 0.68599672,
                "13": 0.91689529,
                "26": 0.84995048,
                "52": 0.82585813
            },
            "price": 8771
        },
        "2011-03-20": {
            "period": {
                "4": 0.25875774,
                "13": 0.80935358,
                "26": 0.73822269,
                "52": 0.75352607
            },
            "price": 8635
        },
        "2011-03-27": {
            "period": {
                "4": 0.33989418,
                "13": 0.79844945,
                "26": 0.74310044,
                "52": 0.74084027
            },
            "price": 8726
        },
        "2011-04-03": {
            "period": {
                "4": 0.44782285,
                "13": 0.79178075,
                "26": 0.81229176,
                "52": 0.76774601
            },
            "price": 8844
        },
        "2011-04-10": {
            "period": {
                "4": 0.58089077,
                "13": 0.82102267,
                "26": 0.80225925,
                "52": 0.77347595
            },
            "price": 8817
        },
        "2011-04-17": {
            "period": {
                "4": 0.75661508,
                "13": 0.7800071,
                "26": 0.71995398,
                "52": 0.72689465
            },
            "price": 8817
        },
        "2011-04-24": {
            "period": {
                "4": 0.86140052,
                "13": 0.80475245,
                "26": 0.73153203,
                "52": 0.75345383
            },
            "price": 8942
        },
        "2011-05-01": {
            "period": {
                "4": 0.88842865,
                "13": 0.85979461,
                "26": 0.79849229,
                "52": 0.75135013
            },
            "price": 9040
        },
        "2011-05-08": {
            "period": {
                "4": 0.88642753,
                "13": 0.85794441,
                "26": 0.8239854,
                "52": 0.79074039
            },
            "price": 9021
        },
        "2011-05-15": {
            "period": {
                "4": 0.94490902,
                "13": 0.80051673,
                "26": 0.81064717,
                "52": 0.81615157
            },
            "price": 9033
        },
        "2011-05-22": {
            "period": {
                "4": 0.86454374,
                "13": 0.76031809,
                "26": 0.93469039,
                "52": 0.8862697
            },
            "price": 9078
        },
        "2011-05-29": {
            "period": {
                "4": 0.56506078,
                "13": 0.76360782,
                "26": 0.93838317,
                "52": 0.93220447
            },
            "price": 9054
        },
        "2011-06-05": {
            "period": {
                "4": 0.49365661,
                "13": 0.77889642,
                "26": 0.93625906,
                "52": 0.91994102
            },
            "price": 9020
        },
        "2011-06-12": {
            "period": {
                "4": 0.36849067,
                "13": 0.70664949,
                "26": 0.89275263,
                "52": 0.92721746
            },
            "price": 8968
        },
        "2011-06-19": {
            "period": {
                "4": 0.19968568,
                "13": 0.79029105,
                "26": 0.88082614,
                "52": 0.86618538
            },
            "price": 8909
        },
        "2011-06-26": {
            "period": {
                "4": 0.28318279,
                "13": 0.79612907,
                "26": 0.87820377,
                "52": 0.89384943
            },
            "price": 8890
        },
        "2011-07-03": {
            "period": {
                "4": 0.18825652,
                "13": 0.71704453,
                "26": 0.83678028,
                "52": 0.93990588
            },
            "price": 9014
        },
        "2011-07-10": {
            "period": {
                "4": 0.70672051,
                "13": 0.79350341,
                "26": 0.88979956,
                "52": 0.97303007
            },
            "price": 9184
        },
        "2011-07-17": {
            "period": {
                "4": 0.77646846,
                "13": 0.80489072,
                "26": 0.87355567,
                "52": 0.94946272
            },
            "price": 8993
        },
        "2011-07-24": {
            "period": {
                "4": 0.69068878,
                "13": 0.700287,
                "26": 0.83291771,
                "52": 0.93705287
            },
            "price": 9125
        },
        "2011-07-31": {
            "period": {
                "4": 0.68064576,
                "13": 0.58346569,
                "26": 0.81749515,
                "52": 0.9077227
            },
            "price": 8999
        },
        "2011-08-07": {
            "period": {
                "4": 0.18308127,
                "13": 0.2853643,
                "26": 0.58315261,
                "52": 0.78386735
            },
            "price": 8549
        },
        "2011-08-14": {
            "period": {
                "4": 0.06582706,
                "13": 0.14659439,
                "26": 0.32056029,
                "52": 0.61852641
            },
            "price": 8474
        },
        "2011-08-21": {
            "period": {
                "4": 0.21197223,
                "13": 0.25601705,
                "26": 0.39259471,
                "52": 0.70612356
            },
            "price": 8479
        },
        "2011-08-28": {
            "period": {
                "4": 0.15213225,
                "13": 0.21754555,
                "26": 0.34994195,
                "52": 0.67985061
            },
            "price": 8467
        },
        "2011-09-04": {
            "period": {
                "4": 0.40875059,
                "13": 0.2819619,
                "26": 0.42015236,
                "52": 0.67985334
            },
            "price": 8676
        },
        "2011-09-11": {
            "period": {
                "4": 0.72384391,
                "13": 0.31388706,
                "26": 0.41472298,
                "52": 0.61390547
            },
            "price": 8639
        },
        "2011-09-18": {
            "period": {
                "4": 0.43658729,
                "13": 0.3097803,
                "26": 0.44253824,
                "52": 0.57070868
            },
            "price": 8546
        },
        "2011-09-25": {
            "period": {
                "4": 0.47237642,
                "13": 0.26518714,
                "26": 0.39347866,
                "52": 0.53344706
            },
            "price": 8342
        },
        "2011-10-02": {
            "period": {
                "4": 0.05906556,
                "13": 0.18956725,
                "26": 0.27473319,
                "52": 0.46988149
            },
            "price": 8285
        },
        "2011-10-09": {
            "period": {
                "4": 0.00332381,
                "13": 0.09535032,
                "26": 0.19718431,
                "52": 0.37884507
            },
            "price": 8211
        },
        "2011-10-16": {
            "period": {
                "4": 0.21207472,
                "13": 0.14957827,
                "26": 0.27587822,
                "52": 0.40521555
            },
            "price": 8309
        },
        "2011-10-23": {
            "period": {
                "4": 0.38691724,
                "13": 0.18629527,
                "26": 0.27910961,
                "52": 0.41620402
            },
            "price": 8360
        },
        "2011-10-30": {
            "period": {
                "4": 0.81278634,
                "13": 0.27960312,
                "26": 0.32564771,
                "52": 0.5018608
            },
            "price": 8756
        },
        "2011-11-06": {
            "period": {
                "4": 0.97744267,
                "13": 0.44349066,
                "26": 0.34205741,
                "52": 0.53164141
            },
            "price": 8652
        },
        "2011-11-13": {
            "period": {
                "4": 0.84683465,
                "13": 0.63190952,
                "26": 0.32629935,
                "52": 0.50118972
            },
            "price": 8511
        },
        "2011-11-20": {
            "period": {
                "4": 0.65139037,
                "13": 0.46194675,
                "26": 0.2901287,
                "52": 0.54952218
            },
            "price": 8421
        },
        "2011-11-27": {
            "period": {
                "4": 0.17773844,
                "13": 0.38382084,
                "26": 0.22052615,
                "52": 0.46437738
            },
            "price": 8191
        },
        "2011-12-04": {
            "period": {
                "4": 0.18875111,
                "13": 0.3328785,
                "26": 0.23700729,
                "52": 0.47606979
            },
            "price": 8500
        },
        "2011-12-11": {
            "period": {
                "4": 0.40819743,
                "13": 0.43981497,
                "26": 0.32277195,
                "52": 0.52081262
            },
            "price": 8479
        },
        "2011-12-18": {
            "period": {
                "4": 0.42961592,
                "13": 0.45139291,
                "26": 0.32675814,
                "52": 0.51712993
            },
            "price": 8465
        },
        "2011-12-25": {
            "period": {
                "4": 0.7535288,
                "13": 0.54625903,
                "26": 0.35012856,
                "52": 0.53468316
            },
            "price": 8578
        },
        "2012-01-01": {
            "period": {
                "4": 0.86569398,
                "13": 0.72046937,
                "26": 0.38723622,
                "52": 0.54037774
            },
            "price": 8649
        },
        "2012-01-08": {
            "period": {
                "4": 0.76520363,
                "13": 0.80617804,
                "26": 0.33181585,
                "52": 0.53436908
            },
            "price": 8666
        },
        "2012-01-15": {
            "period": {
                "4": 0.97605165,
                "13": 0.76091019,
                "26": 0.35341393,
                "52": 0.54999259
            },
            "price": 8702
        },
        "2012-01-22": {
            "period": {
                "4": 0.99409751,
                "13": 0.75336517,
                "26": 0.38743915,
                "52": 0.55822385
            },
            "price": 8803
        },
        "2012-01-29": {
            "period": {
                "4": 0.99446845,
                "13": 0.71978393,
                "26": 0.43618323,
                "52": 0.59379149
            },
            "price": 8961
        },
        "2012-02-05": {
            "period": {
                "4": 0.99983893,
                "13": 0.72435758,
                "26": 0.57685549,
                "52": 0.60092192
            },
            "price": 9009
        },
        "2012-02-12": {
            "period": {
                "4": 1,
                "13": 0.81204602,
                "26": 0.79471522,
                "52": 0.60702145
            },
            "price": 9028
        },
        "2012-02-19": {
            "period": {
                "4": 0.95537341,
                "13": 0.8456855,
                "26": 0.72049692,
                "52": 0.57730751
            },
            "price": 9026
        },
        "2012-02-26": {
            "period": {
                "4": 0.81920619,
                "13": 0.96857431,
                "26": 0.76739417,
                "52": 0.58198132
            },
            "price": 8992
        },
        "2012-03-04": {
            "period": {
                "4": 0.60766998,
                "13": 0.98367953,
                "26": 0.69725249,
                "52": 0.57184404
            },
            "price": 9028
        },
        "2012-03-11": {
            "period": {
                "4": 0.48350297,
                "13": 0.97611165,
                "26": 0.72077171,
                "52": 0.58353222
            },
            "price": 9035
        },
        "2012-03-18": {
            "period": {
                "4": 0.84520773,
                "13": 0.99871608,
                "26": 0.79839045,
                "52": 0.66441988
            },
            "price": 9180
        },
        "2012-03-25": {
            "period": {
                "4": 0.87870126,
                "13": 0.99748827,
                "26": 0.84435796,
                "52": 0.66998534
            },
            "price": 9116
        },
        "2012-04-01": {
            "period": {
                "4": 0.87422884,
                "13": 0.99112571,
                "26": 0.90965537,
                "52": 0.64137628
            },
            "price": 9182
        },
        "2012-04-08": {
            "period": {
                "4": 0.84302276,
                "13": 0.99106144,
                "26": 0.94979788,
                "52": 0.62450425
            },
            "price": 9151
        },
        "2012-04-15": {
            "period": {
                "4": 0.45187877,
                "13": 0.94763376,
                "26": 0.90802272,
                "52": 0.61780384
            },
            "price": 9134
        },
        "2012-04-22": {
            "period": {
                "4": 0.52234583,
                "13": 0.94225425,
                "26": 0.90331965,
                "52": 0.61403165
            },
            "price": 9208
        },
        "2012-04-29": {
            "period": {
                "4": 0.73041506,
                "13": 0.92997249,
                "26": 0.8780112,
                "52": 0.60442845
            },
            "price": 9339
        },
        "2012-05-06": {
            "period": {
                "4": 0.85416396,
                "13": 0.93899696,
                "26": 0.89132772,
                "52": 0.62089035
            },
            "price": 9432
        },
        "2012-05-13": {
            "period": {
                "4": 0.95564023,
                "13": 0.88683987,
                "26": 0.91095631,
                "52": 0.62420873
            },
            "price": 9359
        },
        "2012-05-20": {
            "period": {
                "4": 0.65457752,
                "13": 0.79220137,
                "26": 0.90027195,
                "52": 0.58247898
            },
            "price": 9123
        },
        "2012-05-27": {
            "period": {
                "4": 0.31234219,
                "13": 0.6612879,
                "26": 0.94458238,
                "52": 0.54825784
            },
            "price": 9184
        },
        "2012-06-03": {
            "period": {
                "4": 0.15293758,
                "13": 0.68772879,
                "26": 0.95274552,
                "52": 0.54080184
            },
            "price": 9154
        },
        "2012-06-10": {
            "period": {
                "4": 0.14714572,
                "13": 0.61550564,
                "26": 0.90969539,
                "52": 0.55504993
            },
            "price": 9203
        },
        "2012-06-17": {
            "period": {
                "4": 0.41149033,
                "13": 0.57853189,
                "26": 0.94731636,
                "52": 0.60125458
            },
            "price": 9216
        },
        "2012-06-24": {
            "period": {
                "4": 0.77489848,
                "13": 0.6212424,
                "26": 0.94829388,
                "52": 0.62177684
            },
            "price": 9260
        },
        "2012-07-01": {
            "period": {
                "4": 0.71762254,
                "13": 0.6219584,
                "26": 0.9223411,
                "52": 0.61752665
            },
            "price": 9331
        },
        "2012-07-08": {
            "period": {
                "4": 0.96155736,
                "13": 0.75295525,
                "26": 0.95465328,
                "52": 0.62716762
            },
            "price": 9500
        },
        "2012-07-15": {
            "period": {
                "4": 0.9270047,
                "13": 0.82198307,
                "26": 0.95009563,
                "52": 0.64257199
            },
            "price": 9492
        },
        "2012-07-22": {
            "period": {
                "4": 0.91805335,
                "13": 0.82173894,
                "26": 0.94845888,
                "52": 0.67075589
            },
            "price": 9569
        },
        "2012-07-29": {
            "period": {
                "4": 0.86506924,
                "13": 0.72686884,
                "26": 0.90334065,
                "52": 0.65573592
            },
            "price": 9552
        },
        "2012-08-05": {
            "period": {
                "4": 0.79382777,
                "13": 0.70197382,
                "26": 0.90203575,
                "52": 0.76664053
            },
            "price": 9632
        },
        "2012-08-12": {
            "period": {
                "4": 0.77465119,
                "13": 0.71750396,
                "26": 0.8755655,
                "52": 0.90242761
            },
            "price": 9554
        },
        "2012-08-19": {
            "period": {
                "4": 0.50794428,
                "13": 0.78636479,
                "26": 0.86898734,
                "52": 0.86182889
            },
            "price": 9591
        },
        "2012-08-26": {
            "period": {
                "4": 0.65142779,
                "13": 0.90862602,
                "26": 0.87735816,
                "52": 0.89216457
            },
            "price": 9571
        },
        "2012-09-02": {
            "period": {
                "4": 0.42712834,
                "13": 0.89890779,
                "26": 0.88033632,
                "52": 0.85849131
            },
            "price": 9588
        },
        "2012-09-09": {
            "period": {
                "4": 0.61017057,
                "13": 0.9526244,
                "26": 0.88574038,
                "52": 0.875037
            },
            "price": 9688
        },
        "2012-09-16": {
            "period": {
                "4": 0.95964735,
                "13": 0.95101913,
                "26": 0.86660027,
                "52": 0.90364523
            },
            "price": 9705
        },
        "2012-09-23": {
            "period": {
                "4": 0.81893287,
                "13": 0.90676318,
                "26": 0.84457591,
                "52": 0.91889914
            },
            "price": 9593
        },
        "2012-09-30": {
            "period": {
                "4": 0.45139558,
                "13": 0.80868734,
                "26": 0.7831856,
                "52": 0.93805185
            },
            "price": 9547
        },
        "2012-10-07": {
            "period": {
                "4": 0.2858542,
                "13": 0.60801476,
                "26": 0.76460635,
                "52": 0.95883177
            },
            "price": 9558
        },
        "2012-10-14": {
            "period": {
                "4": 0.22595566,
                "13": 0.62782718,
                "26": 0.82857406,
                "52": 0.94816047
            },
            "price": 9584
        },
        "2012-10-21": {
            "period": {
                "4": 0.42267219,
                "13": 0.61989464,
                "26": 0.82534634,
                "52": 0.94487024
            },
            "price": 9682
        },
        "2012-10-28": {
            "period": {
                "4": 0.68473911,
                "13": 0.64478527,
                "26": 0.75744385,
                "52": 0.91044671
            },
            "price": 9581
        },
        "2012-11-04": {
            "period": {
                "4": 0.62645447,
                "13": 0.46273473,
                "26": 0.65666743,
                "52": 0.88797621
            },
            "price": 9625
        },
        "2012-11-11": {
            "period": {
                "4": 0.60628384,
                "13": 0.5021286,
                "26": 0.68767224,
                "52": 0.91173394
            },
            "price": 9548
        },
        "2012-11-18": {
            "period": {
                "4": 0.19695081,
                "13": 0.3996532,
                "26": 0.69741332,
                "52": 0.90814551
            },
            "price": 9437
        },
        "2012-11-25": {
            "period": {
                "4": 0.24555524,
                "13": 0.38437127,
                "26": 0.79931541,
                "52": 0.96244159
            },
            "price": 9524
        },
        "2012-12-02": {
            "period": {
                "4": 0.46999948,
                "13": 0.48107251,
                "26": 0.82346332,
                "52": 0.96994115
            },
            "price": 9590
        },
        "2012-12-09": {
            "period": {
                "4": 0.57461735,
                "13": 0.49597017,
                "26": 0.8823772,
                "52": 0.96277541
            },
            "price": 9649
        },
        "2012-12-16": {
            "period": {
                "4": 0.95122312,
                "13": 0.50979108,
                "26": 0.88113389,
                "52": 0.9770583
            },
            "price": 9651
        },
        "2012-12-23": {
            "period": {
                "4": 0.99630362,
                "13": 0.57311549,
                "26": 0.85773151,
                "52": 0.97348548
            },
            "price": 9778
        },
        "2012-12-30": {
            "period": {
                "4": 0.99194997,
                "13": 0.80151461,
                "26": 0.8874858,
                "52": 0.96870565
            },
            "price": 9774
        },
        "2013-01-06": {
            "period": {
                "4": 0.97338999,
                "13": 0.83598673,
                "26": 0.80730204,
                "52": 0.96934005
            },
            "price": 9825
        },
        "2013-01-13": {
            "period": {
                "4": 0.98214286,
                "13": 0.86149508,
                "26": 0.83880568,
                "52": 0.97154241
            },
            "price": 9857
        },
        "2013-01-20": {
            "period": {
                "4": 0.99875052,
                "13": 0.84844123,
                "26": 0.82455238,
                "52": 0.96851296
            },
            "price": 9902
        },
        "2013-01-27": {
            "period": {
                "4": 0.99986985,
                "13": 0.9089864,
                "26": 0.88076339,
                "52": 0.95788899
            },
            "price": 9946
        },
        "2013-02-03": {
            "period": {
                "4": 1,
                "13": 0.95266504,
                "26": 0.85838089,
                "52": 0.95133762
            },
            "price": 9947
        },
        "2013-02-10": {
            "period": {
                "4": 0.96540179,
                "13": 0.94403623,
                "26": 0.85544457,
                "52": 0.93736758
            },
            "price": 9948
        },
        "2013-02-17": {
            "period": {
                "4": 0.94531738,
                "13": 0.9988717,
                "26": 0.91124083,
                "52": 0.95105421
            },
            "price": 10003
        },
        "2013-02-24": {
            "period": {
                "4": 0.91517694,
                "13": 0.99998597,
                "26": 0.91555514,
                "52": 0.95580674
            },
            "price": 10002
        },
        "2013-03-03": {
            "period": {
                "4": 0.79295573,
                "13": 0.99974836,
                "26": 0.91517077,
                "52": 0.95708267
            },
            "price": 10077
        },
        "2013-03-10": {
            "period": {
                "4": 0.96457368,
                "13": 0.99978838,
                "26": 0.93039715,
                "52": 0.96432188
            },
            "price": 10144
        },
        "2013-03-17": {
            "period": {
                "4": 0.96347876,
                "13": 0.9996995,
                "26": 0.92906724,
                "52": 0.95758974
            },
            "price": 10200
        },
        "2013-03-24": {
            "period": {
                "4": 0.89919239,
                "13": 0.99910479,
                "26": 0.93538607,
                "52": 0.95198333
            },
            "price": 10146
        },
        "2013-03-31": {
            "period": {
                "4": 0.93858028,
                "13": 0.99839421,
                "26": 0.98155817,
                "52": 0.95700335
            },
            "price": 10220
        },
        "2013-04-07": {
            "period": {
                "4": 0.91662979,
                "13": 0.99908416,
                "26": 0.98978379,
                "52": 0.96320687
            },
            "price": 10374
        },
        "2013-04-14": {
            "period": {
                "4": 0.96637794,
                "13": 0.9994156,
                "26": 0.99486186,
                "52": 0.98511059
            },
            "price": 10518
        },
        "2013-04-21": {
            "period": {
                "4": 0.99276343,
                "13": 0.99929374,
                "26": 0.99443588,
                "52": 0.98455213
            },
            "price": 10507
        },
        "2013-04-28": {
            "period": {
                "4": 0.99907753,
                "13": 0.9993553,
                "26": 0.99794268,
                "52": 0.9831879
            },
            "price": 10622
        },
        "2013-05-05": {
            "period": {
                "4": 0.99934109,
                "13": 0.99947899,
                "26": 0.9993208,
                "52": 0.97936347
            },
            "price": 10659
        },
        "2013-05-12": {
            "period": {
                "4": 0.99934109,
                "13": 0.99992513,
                "26": 0.99966369,
                "52": 0.9859401
            },
            "price": 10743
        },
        "2013-05-19": {
            "period": {
                "4": 0.99996258,
                "13": 0.99995194,
                "26": 0.99999945,
                "52": 0.99531046
            },
            "price": 10832
        },
        "2013-05-26": {
            "period": {
                "4": 0.86587132,
                "13": 0.99608739,
                "26": 0.99996567,
                "52": 0.99845085
            },
            "price": 10625
        },
        "2013-06-02": {
            "period": {
                "4": 0.35226533,
                "13": 0.87909526,
                "26": 0.98097571,
                "52": 0.98394816
            },
            "price": 10363
        },
        "2013-06-09": {
            "period": {
                "4": 0.09409654,
                "13": 0.63965479,
                "26": 0.90191102,
                "52": 0.95892428
            },
            "price": 10245
        },
        "2013-06-16": {
            "period": {
                "4": 0.01855672,
                "13": 0.51619912,
                "26": 0.83471722,
                "52": 0.93056667
            },
            "price": 10150
        },
        "2013-06-23": {
            "period": {
                "4": 0.00409172,
                "13": 0.4681183,
                "26": 0.78025832,
                "52": 0.894144
            },
            "price": 9917
        },
        "2013-06-30": {
            "period": {
                "4": 0.0613823,
                "13": 0.37594756,
                "26": 0.67032465,
                "52": 0.8515851
            },
            "price": 10165
        },
        "2013-07-07": {
            "period": {
                "4": 0.37950984,
                "13": 0.44189655,
                "26": 0.74106962,
                "52": 0.83869909
            },
            "price": 10185
        },
        "2013-07-14": {
            "period": {
                "4": 0.62087249,
                "13": 0.39235041,
                "26": 0.75991604,
                "52": 0.86359068
            },
            "price": 10393
        },
        "2013-07-21": {
            "period": {
                "4": 0.79933329,
                "13": 0.43247176,
                "26": 0.79000457,
                "52": 0.87445604
            },
            "price": 10418
        },
        "2013-07-28": {
            "period": {
                "4": 0.98399267,
                "13": 0.37411112,
                "26": 0.7680611,
                "52": 0.88436156
            },
            "price": 10354
        },
        "2013-08-04": {
            "period": {
                "4": 0.6733132,
                "13": 0.26575084,
                "26": 0.68609398,
                "52": 0.82110199
            },
            "price": 10212
        },
        "2013-08-11": {
            "period": {
                "4": 0.30405137,
                "13": 0.16907198,
                "26": 0.63090734,
                "52": 0.78019249
            },
            "price": 10147
        },
        "2013-08-18": {
            "period": {
                "4": 0.0108939,
                "13": 0.11567245,
                "26": 0.56474654,
                "52": 0.77025424
            },
            "price": 9985
        },
        "2013-08-25": {
            "period": {
                "4": 0,
                "13": 0.06517492,
                "26": 0.43505865,
                "52": 0.67073839
            },
            "price": 9902
        },
        "2013-09-01": {
            "period": {
                "4": 0.01430068,
                "13": 0.12543613,
                "26": 0.42607061,
                "52": 0.66450015
            },
            "price": 9865
        },
        "2013-09-08": {
            "period": {
                "4": 0.02079537,
                "13": 0.18034634,
                "26": 0.33405277,
                "52": 0.60923721
            },
            "price": 9787
        },
        "2013-09-15": {
            "period": {
                "4": 0.28751367,
                "13": 0.32944551,
                "26": 0.37914721,
                "52": 0.64233339
            },
            "price": 9991
        },
        "2013-09-22": {
            "period": {
                "4": 0.80839526,
                "13": 0.49724885,
                "26": 0.47081183,
                "52": 0.7149041
            },
            "price": 10210
        },
        "2013-09-29": {
            "period": {
                "4": 0.85623341,
                "13": 0.61883572,
                "26": 0.48133975,
                "52": 0.77871561
            },
            "price": 10150
        },
        "2013-10-06": {
            "period": {
                "4": 0.88320459,
                "13": 0.43714954,
                "26": 0.4151497,
                "52": 0.76485987
            },
            "price": 10066
        },
        "2013-10-13": {
            "period": {
                "4": 0.71759976,
                "13": 0.32609453,
                "26": 0.31115429,
                "52": 0.74597253
            },
            "price": 10154
        },
        "2013-10-20": {
            "period": {
                "4": 0.71991976,
                "13": 0.36742006,
                "26": 0.36595376,
                "52": 0.7791017
            },
            "price": 10351
        },
        "2013-10-27": {
            "period": {
                "4": 0.82846015,
                "13": 0.47826121,
                "26": 0.38811845,
                "52": 0.82369082
            },
            "price": 10395
        },
        "2013-11-03": {
            "period": {
                "4": 0.91116657,
                "13": 0.5910088,
                "26": 0.36452134,
                "52": 0.83621505
            },
            "price": 10337
        },
        "2013-11-10": {
            "period": {
                "4": 0.81956411,
                "13": 0.60784125,
                "26": 0.28269007,
                "52": 0.80063501
            },
            "price": 10218
        },
        "2013-11-17": {
            "period": {
                "4": 0.40283834,
                "13": 0.59322139,
                "26": 0.21979419,
                "52": 0.80988134
            },
            "price": 10235
        },
        "2013-11-24": {
            "period": {
                "4": 0.09992581,
                "13": 0.74809124,
                "26": 0.20696562,
                "52": 0.79860062
            },
            "price": 10120
        },
        "2013-12-01": {
            "period": {
                "4": 0.03508792,
                "13": 0.70618787,
                "26": 0.28691022,
                "52": 0.75420335
            },
            "price": 10136
        },
        "2013-12-08": {
            "period": {
                "4": 0.05451505,
                "13": 0.71959623,
                "26": 0.37264865,
                "52": 0.71068122
            },
            "price": 10047
        },
        "2013-12-15": {
            "period": {
                "4": 0.07701544,
                "13": 0.56681288,
                "26": 0.40687799,
                "52": 0.66683683
            },
            "price": 9929
        },
        "2013-12-22": {
            "period": {
                "4": 0.08991859,
                "13": 0.35306921,
                "26": 0.41570512,
                "52": 0.63005204
            },
            "price": 10013
        },
        "2013-12-29": {
            "period": {
                "4": 0.35012918,
                "13": 0.38350106,
                "26": 0.52884082,
                "52": 0.63886465
            },
            "price": 10078
        },
        "2014-01-05": {
            "period": {
                "4": 0.55814472,
                "13": 0.4694492,
                "26": 0.43566502,
                "52": 0.64279585
            },
            "price": 10084
        },
        "2014-01-12": {
            "period": {
                "4": 0.79085863,
                "13": 0.54940704,
                "26": 0.39638322,
                "52": 0.63831821
            },
            "price": 10141
        },
        "2014-01-19": {
            "period": {
                "4": 1,
                "13": 0.41967053,
                "26": 0.34797642,
                "52": 0.64225892
            },
            "price": 10225
        },
        "2014-01-26": {
            "period": {
                "4": 0.99997397,
                "13": 0.31723272,
                "26": 0.38277931,
                "52": 0.64265025
            },
            "price": 10224
        },
        "2014-02-02": {
            "period": {
                "4": 0.76173827,
                "13": 0.22513996,
                "26": 0.41669038,
                "52": 0.59412501
            },
            "price": 10183
        },
        "2014-02-09": {
            "period": {
                "4": 0.67483601,
                "13": 0.34474926,
                "26": 0.50610391,
                "52": 0.60545517
            },
            "price": 10191
        },
        "2014-02-16": {
            "period": {
                "4": 0.74870171,
                "13": 0.62208074,
                "26": 0.64077685,
                "52": 0.63535705
            },
            "price": 10329
        },
        "2014-02-23": {
            "period": {
                "4": 0.82267154,
                "13": 0.77300236,
                "26": 0.8376861,
                "52": 0.66405767
            },
            "price": 10403
        },
        "2014-03-02": {
            "period": {
                "4": 0.99624343,
                "13": 0.87026462,
                "26": 0.86135092,
                "52": 0.67649383
            },
            "price": 10420
        },
        "2014-03-09": {
            "period": {
                "4": 1,
                "13": 0.93945713,
                "26": 0.9112665,
                "52": 0.65695228
            },
            "price": 10485
        },
        "2014-03-16": {
            "period": {
                "4": 0.85594219,
                "13": 0.94344123,
                "26": 0.84754423,
                "52": 0.61902418
            },
            "price": 10403
        },
        "2014-03-23": {
            "period": {
                "4": 0.56563183,
                "13": 0.97011737,
                "26": 0.74404879,
                "52": 0.60866563
            },
            "price": 10374
        },
        "2014-03-30": {
            "period": {
                "4": 0.37628364,
                "13": 0.93728627,
                "26": 0.70562131,
                "52": 0.5903225
            },
            "price": 10385
        },
        "2014-04-06": {
            "period": {
                "4": 0.43398421,
                "13": 0.95173152,
                "26": 0.79289103,
                "52": 0.58807575
            },
            "price": 10474
        },
        "2014-04-13": {
            "period": {
                "4": 0.80055023,
                "13": 0.953192,
                "26": 0.84274712,
                "52": 0.5333483
            },
            "price": 10508
        },
        "2014-04-20": {
            "period": {
                "4": 0.93928962,
                "13": 0.93783745,
                "26": 0.76399123,
                "52": 0.51392416
            },
            "price": 10575
        },
        "2014-04-27": {
            "period": {
                "4": 0.99507041,
                "13": 0.94834552,
                "26": 0.73350278,
                "52": 0.51045809
            },
            "price": 10637
        },
        "2014-05-04": {
            "period": {
                "4": 0.99310183,
                "13": 0.99040672,
                "26": 0.7555053,
                "52": 0.50034771
            },
            "price": 10673
        },
        "2014-05-11": {
            "period": {
                "4": 0.99444242,
                "13": 0.99476226,
                "26": 0.86969676,
                "52": 0.49426849
            },
            "price": 10775
        },
        "2014-05-18": {
            "period": {
                "4": 0.99992191,
                "13": 0.99298693,
                "26": 0.94678919,
                "52": 0.49710934
            },
            "price": 10769
        },
        "2014-05-25": {
            "period": {
                "4": 0.98371284,
                "13": 0.98050104,
                "26": 0.95764214,
                "52": 0.49551014
            },
            "price": 10758
        },
        "2014-06-01": {
            "period": {
                "4": 0.96911931,
                "13": 0.97947247,
                "26": 0.98039383,
                "52": 0.64555789
            },
            "price": 10841
        },
        "2014-06-08": {
            "period": {
                "4": 0.97252935,
                "13": 0.98410306,
                "26": 0.99365517,
                "52": 0.79388912
            },
            "price": 10991
        },
        "2014-06-15": {
            "period": {
                "4": 0.84690624,
                "13": 0.9929309,
                "26": 0.99650878,
                "52": 0.83861291
            },
            "price": 10872
        },
        "2014-06-22": {
            "period": {
                "4": 0.73007015,
                "13": 0.98414939,
                "26": 0.99770652,
                "52": 0.84824637
            },
            "price": 10924
        },
        "2014-06-29": {
            "period": {
                "4": 0.72163942,
                "13": 0.99052961,
                "26": 0.9967975,
                "52": 0.90329941
            },
            "price": 10914
        },
        "2014-07-06": {
            "period": {
                "4": 0.58242822,
                "13": 0.9863753,
                "26": 0.99666839,
                "52": 0.87082211
            },
            "price": 10931
        },
        "2014-07-13": {
            "period": {
                "4": 0.58245262,
                "13": 0.97494955,
                "26": 0.99467609,
                "52": 0.83778699
            },
            "price": 10953
        },
        "2014-07-20": {
            "period": {
                "4": 0.95158755,
                "13": 0.98248474,
                "26": 0.99467484,
                "52": 0.81547389
            },
            "price": 11002
        },
        "2014-07-27": {
            "period": {
                "4": 0.96752818,
                "13": 0.97699612,
                "26": 0.99440171,
                "52": 0.83150679
            },
            "price": 11049
        },
        "2014-08-03": {
            "period": {
                "4": 0.75932717,
                "13": 0.94639289,
                "26": 0.99705395,
                "52": 0.86809107
            },
            "price": 10950
        },
        "2014-08-10": {
            "period": {
                "4": 0.43075802,
                "13": 0.78313178,
                "26": 0.98645133,
                "52": 0.87435809
            },
            "price": 10873
        },
        "2014-08-17": {
            "period": {
                "4": 0.4157968,
                "13": 0.76467178,
                "26": 0.98074035,
                "52": 0.91313941
            },
            "price": 11028
        },
        "2014-08-24": {
            "period": {
                "4": 0.58656875,
                "13": 0.86715804,
                "26": 0.981619,
                "52": 0.9759895
            },
            "price": 11114
        },
        "2014-08-31": {
            "period": {
                "4": 0.65277326,
                "13": 0.83221601,
                "26": 0.97511635,
                "52": 0.9770641
            },
            "price": 11067
        },
        "2014-09-07": {
            "period": {
                "4": 0.9135793,
                "13": 0.75854716,
                "26": 0.96835929,
                "52": 0.98455787
            },
            "price": 11101
        },
        "2014-09-14": {
            "period": {
                "4": 0.77044396,
                "13": 0.71998576,
                "26": 0.97438483,
                "52": 0.97427277
            },
            "price": 11001
        },
        "2014-09-21": {
            "period": {
                "4": 0.15649241,
                "13": 0.51766221,
                "26": 0.89095481,
                "52": 0.90303735
            },
            "price": 10823
        },
        "2014-09-28": {
            "period": {
                "4": 0.04221386,
                "13": 0.33845955,
                "26": 0.8277008,
                "52": 0.84974694
            },
            "price": 10704
        },
        "2014-10-05": {
            "period": {
                "4": 0.01620744,
                "13": 0.27641868,
                "26": 0.76007107,
                "52": 0.8574622
            },
            "price": 10721
        },
        "2014-10-12": {
            "period": {
                "4": 0.06612316,
                "13": 0.31914708,
                "26": 0.7445926,
                "52": 0.87903137
            },
            "price": 10810
        },
        "2014-10-19": {
            "period": {
                "4": 0.36813762,
                "13": 0.31064985,
                "26": 0.76245502,
                "52": 0.84171821
            },
            "price": 10822
        },
        "2014-10-26": {
            "period": {
                "4": 0.87372449,
                "13": 0.42679113,
                "26": 0.79200078,
                "52": 0.84376463
            },
            "price": 11055
        },
        "2014-11-02": {
            "period": {
                "4": 0.99802166,
                "13": 0.60850313,
                "26": 0.84431891,
                "52": 0.88641878
            },
            "price": 11178
        },
        "2014-11-09": {
            "period": {
                "4": 1,
                "13": 0.80642082,
                "26": 0.87151721,
                "52": 0.94290637
            },
            "price": 11254
        },
        "2014-11-16": {
            "period": {
                "4": 0.99455468,
                "13": 0.77301838,
                "26": 0.84380316,
                "52": 0.9626049
            },
            "price": 11266
        },
        "2014-11-23": {
            "period": {
                "4": 0.93981512,
                "13": 0.66049031,
                "26": 0.8348807,
                "52": 0.96474095
            },
            "price": 11228
        },
        "2014-11-30": {
            "period": {
                "4": 0.86987356,
                "13": 0.71013609,
                "26": 0.84090032,
                "52": 0.97766466
            },
            "price": 11372
        },
        "2014-12-07": {
            "period": {
                "4": 0.82335648,
                "13": 0.76185794,
                "26": 0.83474197,
                "52": 0.98723359
            },
            "price": 11399
        },
        "2014-12-14": {
            "period": {
                "4": 0.82200288,
                "13": 0.78717103,
                "26": 0.83579449,
                "52": 0.9908356
            },
            "price": 11389
        },
        "2014-12-21": {
            "period": {
                "4": 0.80131651,
                "13": 0.92506131,
                "26": 0.8469775,
                "52": 0.99256938
            },
            "price": 11442
        },
        "2014-12-28": {
            "period": {
                "4": 0.87877447,
                "13": 0.99232954,
                "26": 0.88182766,
                "52": 0.99341436
            },
            "price": 11540
        },
        "2015-01-04": {
            "period": {
                "4": 0.86365707,
                "13": 0.9982677,
                "26": 0.89427617,
                "52": 0.99414044
            },
            "price": 11577
        },
        "2015-01-11": {
            "period": {
                "4": 0.92585283,
                "13": 0.99871487,
                "26": 0.91828255,
                "52": 0.99453593
            },
            "price": 11764
        },
        "2015-01-18": {
            "period": {
                "4": 0.99979175,
                "13": 0.9993902,
                "26": 0.93976837,
                "52": 0.99610446
            },
            "price": 11886
        },
        "2015-01-25": {
            "period": {
                "4": 0.99975271,
                "13": 0.99934581,
                "26": 0.94976875,
                "52": 0.99670832
            },
            "price": 12002
        },
        "2015-02-01": {
            "period": {
                "4": 0.99987635,
                "13": 0.99916723,
                "26": 0.96956079,
                "52": 0.99864326
            },
            "price": 12061
        },
        "2015-02-08": {
            "period": {
                "4": 0.94786027,
                "13": 0.99071156,
                "26": 0.97711717,
                "52": 0.99794896
            },
            "price": 12028
        }
    }
}